[
  {
    "file_path": "C:\\Users\\vasis\\Downloads\\resumeData\\180517_Vasanthi Kasinathan.pdf",
    "name": "Name : Vasanthi Kasinathan",
    "raw_text": "1\nTHE SEARCH SPECIALISTS FOR THE FUNDS INDUSTRY\nLONDON | LUXEMBOURG | AMSTERDAM | SINGAPORE | HONG KONG\nNAME : VASANTHI KASINATHAN\nNATIONAL : SINGAPORE P.R.\nCURRENT DRAWN SALARY : $9K PER/MTH\nNOTICE PERIOD : 2 MONTHS\nEDUCATION DETAILS\n• SINGAPORE ACCOUNTANTS ACADEMY\nACCA (1997)\nFCCA (2002)\n• INSTITUTE OF BUSINESS STUDIES (1987)\nLCCI DIPLOMA IN COST ACCOUNTING\n• METHODIST GIRLS SECONDARY SCHOOL, MALAYSIA (1985)\nGCE ‘O’ LEVELS\nLANGUAGE SKILLS\n• FLUENT IN ENGLISH, MALAY\nTECHNICAL SKILLS\n• PROFICIENT IN MICROSOFT OFFICE SUITE\n• JDE ONE WORLD, FINANCEONE, QUICKBOOKS, IBM S36, ACCPAC (ACCOUNTING SOFTWARES)\n• EASYPAY, READYPAY (PAYROLL SOFTWARE)\nPROFESSIONAL EXPERIENCE\nPACIFIC STAR FINANCIAL PTE LTD OCT 2010 - PRESENT\nFUND CONTROLLER\nPortfolio 1 :-\nReal estate close ended fund with assets located in Thailand, Korea, Singapore and Malaysia with total\ninvestment size of ~EUR1.25bn. The fund invested in prime commercial and residential real estate in gateway\nAsian cities in Singapore, Malaysia, Thailand, Hong Kong, China, Japan and Korea.\nPortfolio 2 :-\nReal estate close ended fund with assets located in Thailand and Malaysia. The fund invested in residential\nreal estate in Malaysia.\nKey Responsibilities：\nMonthly/Quarterly\n• Overseeing all aspects of financial control in the fund management business\n• Review monthly reports prepared by external property managers\n• Review SPVs onshore/offshore and holding company books at entity and consolidation level and\n1\nT: +852 3478 3956 | Level 12, BOC Group Life Assurance Tower, 134-136 Des Voeux Road Central, Hong Kong\nT: +65 6635 7611 | Address: Chevron House, 30 Raffles Place, #09-05, Singapore 048622\nE: office@fundspartnership.com | W: www.fundspartnership.com Employment Agency License Number: 15C7420\nThis CV has been provided by Funds Partnership. Any engagement of this or any associated individual by the recipient Company or any associated business\nas a consequence of this introduction will result in a charge as per our standard or otherwise agreed Terms & Conditions of Business. If the candidate is\nemployed by the firm in receipt of this resume within the next 12 months the firm agrees to abide by the Funds Partnership Terms and Conditions as\npreviously agreed.\n2\nTHE SEARCH SPECIALISTS FOR THE FUNDS INDUSTRY\nLONDON | LUXEMBOURG | AMSTERDAM | SINGAPORE | HONG KONG\nensure reconciliation on monthly basis (bank, inter-company, accruals etc)\n• Maintain SPVs bank accounts and serve as director of SPVs\n• Manage bank mandates, annual statutory audit, annual budgets, forecasts, annual tax returns and\nquarterly GST returns\n• Review quarterly reports to investors, budget variances and ad-hoc analysis\n• Involved in Business Planning, P&L, Balance sheet & liquidity planning\n• Overseeing internal financial controls\n• Liaise with banks/trustees on loan compliance ensure no breaching of loan covenants etc\n• Undertake Cash management\nAnnually\n• Co-ordinate with Asset Management team on annual budgets\n• Liaise with auditors on annual audit exercise and tax agents on annual tax returns\nAd-hoc\n• Assist Fund Management team on external refinancing of SGD650 million loan\n• Co-ordinate with Fund Management team on due diligence of divestment, cash repatriation during the\nlife of investment and divestment: -\n• Korea - KRW 235bn\n• Singapore - SGD 970mn\n• Malaysia – MYR 160mn\n• Thailand – THB 2.3 bn\n• Calculate capital call and distribution to investors\n• Calculate performance of fund IRR\nFRASERS CENTREPOINT ASSET MANAGEMENT (COMMERCIAL) LTD (REIT MANAGER) APR 2005 – MAR 2010\nFORMERLY KNOWN AS ALLCO (SINGAPORE) LIMITED (ACQUIRED BY FRASERS GROUP IN AUGUST 2008)\nALLCO (SINGAPORE) LIMITED\n(ALLCO FINANCE GROUP JV WITH INTERNATIONAL MEZZANINE FUND MANAGEMENT LTD)\nSENIOR FINANCE MANAGER\nKey Responsibilities:\nREIT\n• Consolidation and management reporting of the Group’s and REIT’s statutory accounts\n• Responsible for SGX reporting requirements, announcement and review of subsidiaries’ financial\nreports\n• Direct the budget process and manage internal financial controls as well as statutory compliance of\nlocal group of companies\n• Implementation of accounting procedures and financial management functions including financial\naccounting, cash management, budgetary matters, external audit, management reporting.\n• Advise operations on treasury matters such as loan roll-over notices, bank covenants, prepare cashflow\nprojections, etc.\nCORPORATE\n• Manage the accounting and operations of Singapore entity\n• Reporting to Head office based in Australia on monthly basis (Allco Finance Group)\n• Preparation of annual reports, tax returns and co-ordinate with the Company Secretary on annual return\nand other corporate secretarial matters\n2\nT: +852 3478 3956 | Level 12, BOC Group Life Assurance Tower, 134-136 Des Voeux Road Central, Hong Kong\nT: +65 6635 7611 | Address: Chevron House, 30 Raffles Place, #09-05, Singapore 048622\nE: office@fundspartnership.com | W: www.fundspartnership.com Employment Agency License Number: 15C7420\nThis CV has been provided by Funds Partnership. Any engagement of this or any associated individual by the recipient Company or any associated business\nas a consequence of this introduction will result in a charge as per our standard or otherwise agreed Terms & Conditions of Business. If the candidate is\nemployed by the firm in receipt of this resume within the next 12 months the firm agrees to abide by the Funds Partnership Terms and Conditions as\npreviously agreed.\n3\nTHE SEARCH SPECIALISTS FOR THE FUNDS INDUSTRY\nLONDON | LUXEMBOURG | AMSTERDAM | SINGAPORE | HONG KONG\n• Supervise GST reporting\n• Supervise payroll, CPF reporting and IR8A\n• Liaise with bankers, auditors, tax agents and external company secretary and reporting on overall\ninternal control and giving recommendations on improvement\n• Responsible for due diligence on sale of Allco (Singapore) Ltd to Frasers & Neave Group\n• Integration of accounting systems (JDE One World & FinanceOne)\n• Other projects as assigned\nINTERNATIONAL MEZZANINE FUND MANAGEMENT LTD (FUND MANAGEMENT)\nFINANCE MANAGER\nPERIOD: 2004 – 2005\nINTERNET SECURITY SYSTEMS PTE LTD (SOUTHEAST ASIA & INDIA) (INTERNET SECURITY PROVIDER)\nACCOUNTANT CUM HR & ADMIN MANAGER\nPERIOD: 2000 – 2004\nTANG CHENG LIN & CO (PUBLIC ACCOUNTANT)\nPAYROLL & ACCOUNTS EXECUTIVE\nPERIOD: 1998 - 1999\nBSN COMMERCIAL BANK, MELAKA, MALAYSIA (BANK)\nBANK OFFICER\nPERIOD: 1997 – 1998\nMATSUSHITA DENSHI (S) PTE LTD (SEMI-CONDUCTOR)\nACCOUNTS ASSISTANT\nPERIOD: 1995 - 1997\nNEPTUNE ORIENT LINES LTD (NOL) (SHIPPING)\nASSISTANT EXECUTIVE\nPERIOD: 1990 - 1995\n3\nT: +852 3478 3956 | Level 12, BOC Group Life Assurance Tower, 134-136 Des Voeux Road Central, Hong Kong\nT: +65 6635 7611 | Address: Chevron House, 30 Raffles Place, #09-05, Singapore 048622\nE: office@fundspartnership.com | W: www.fundspartnership.com Employment Agency License Number: 15C7420\nThis CV has been provided by Funds Partnership. Any engagement of this or any associated individual by the recipient Company or any associated business\nas a consequence of this introduction will result in a charge as per our standard or otherwise agreed Terms & Conditions of Business. If the candidate is\nemployed by the firm in receipt of this resume within the next 12 months the firm agrees to abide by the Funds Partnership Terms and Conditions as\npreviously agreed.\n",
    "skills": [
      "accounting",
      "finance"
    ],
    "experience": 0,
    "education": [
      "EDUCATION DETAILS",
      "• SINGAPORE ACCOUNTANTS ACADEMY",
      "ACCA (1997)",
      "FCCA (2002)",
      "TECHNICAL SKILLS",
      "Real estate close ended fund with assets located in Thailand, Korea, Singapore and Malaysia with total",
      "Real estate close ended fund with assets located in Thailand and Malaysia. The fund invested in residential",
      "as a consequence of this introduction will result in a charge as per our standard or otherwise agreed Terms & Conditions of Business. If the candidate is",
      "• Manage bank mandates, annual statutory audit, annual budgets, forecasts, annual tax returns and",
      "• Undertake Cash management",
      "• Co-ordinate with Fund Management team on due diligence of divestment, cash repatriation during the",
      "• Calculate capital call and distribution to investors",
      "• Calculate performance of fund IRR",
      "local group of companies",
      "accounting, cash management, budgetary matters, external audit, management reporting.",
      "• Advise operations on treasury matters such as loan roll-over notices, bank covenants, prepare cashflow",
      "as a consequence of this introduction will result in a charge as per our standard or otherwise agreed Terms & Conditions of Business. If the candidate is",
      "as a consequence of this introduction will result in a charge as per our standard or otherwise agreed Terms & Conditions of Business. If the candidate is"
    ],
    "personal_info": {
      "email": "office@fundspartnership.com",
      "phone": "+852 3478 3956"
    },
    "timestamp": "2025-06-12T11:11:55.349218"
  },
  {
    "file_path": "C:\\Users\\vasis\\Downloads\\resumeData\\CV-Gloria Cheng2018.pdf",
    "name": "Gender: Female",
    "raw_text": "CURRICULUM VITAE\nNAME: Gloria Cheng Ge Fang\nE-MAIL: gefang@singnet.com.sg\nHP: 65-94761969\nGENDER: Female\nDATE OF BIRTH: Aug. / 1974\nADDRESS: 36 St.Patrick’s Road Tierra Vue #05-04 Singapore 424160\nNATIONALITY: Chinese / 20 years Singapore P.R\nMARITAL STATUS: Married\nEDUCATION: MBA in Finance with Distinction\nThe University of Nottingham, UK\n2004 – 2006\nBest Overall Performance and Best Dissertation Award\nPublished Research Paper <Electronics: A case study of\nEconomic Value Added in Target Costing> in Academic\nJournal <Management Accounting Research> by Elsevier\nLtd in Sept 2012\nBachelor of Economics (International Accounting)\nShanghai International Studies University\n1992 - 1996\nQUALIFICATION: Fellow member of Association of Chartered Certified\nAccountant (ACCA), UK\nACCA Worldwide Prize Winner (1993)\nChartered Accountant, Singapore\nCertified Green Belt\nAwarded by University of Michigan College of\nEngineering\nWORKING EXPERIENCE:\nCompany: Armstrong Asset management Pte. Ltd.\nFrom Aug 2017 to date\nNature of the firm: An independent asset manager specialized in clean energy\nsector with investment into clean energy infrastructure\nassets in South East Asia countries that leave a long term\npositive impact on society and the natural environment.\nPosition Held: Financial Controller (contract) Aug’17 to date\nJob Description: Fund Finance, tax & Administration\n1. Reporting to Managing Partner, the FC role is responsible\nfor financial control and all accounting activities as well as\ntax reporting of the Master-Feeder Fund and its 10 SPVs\n2. Review quarterly management accounts prepared by the\nFund Administrator for all the Fund and SPVs. Prepare\nquarterly investor report to LPs and assist in calculations of\nreturns (Gross and Net IRR & Multiples for Fund,\nPortfolio, etc) on monthly, quarterly and annual basis\n3. Responsible for investor capital calls, distribution,\ninvestment exit repayment, management fee calculation\nand investors questionnaires\n4. Responsible for the annual valuation of portfolio\ncompanies held by SPVs and the Fund\n5. Managing cash flow of the fund and its SPVs, maintain\nMaster-Feeder Fund and SPV bank accounts to ensure\nefficient cash management and proper internal control\nmaintain the fund flow statement on regular basis.\n6. Oversee the external audit process on year end and ensure\naccurate and timely delivery of audited financial statements\n7. Responsible for annual tax return, ECI filing, annual\ndeclaration for MAS S13X & S13R as well as FATCA and\nCRS return filing for the Master-Feeder Fund and SPVs,\nprepare semi-annual GST remission report of the Fund\n8. Liaise with and maintain constructive working relationship\nwith fund administrator, tax agents, auditor, banks, legal\ncounsels, company secretaries and etc\n9. Perform all day-to-day duties linked to the general\nadministration and strong support to the operation of the\nfund\n10. Assist in investment structure set up for new deals to ensure\nthat they are tax and operational efficient. Assist in\ninvestment exit in terms of Gross /net IRR calculation,\nwater fall analysis, deal cost tracking, SPV winding up and\ncorrespondence with MAS, ACRA etc.\nManager Accounting, Tax & Reporting\n1. Review monthly management accounts prepared by the\nService Provider\n2. Managing cash flow and act as the bank authorized signer\n3. Coordinate with internal & external auditors to ensure all\ndocumentation is provided in a timely manner and that\naudited annual accounts are completed in time\n4. Coordinate with tax agent to ensure proper filing of tax\nreturns and assist in ECI and PIC calculations\n5. Responsible for annual MAS filing for Form 25B, FSI-FM\nreturn Monitoring CMS license ensuring Fund’s AUM not\nexceeding the threshold\nCompany: Henderson Global Investors (Singapore) Ltd\nFrom Dec’05 to July’15\nNature of the firm: Asia Pacific headquarter of UK / Australia listed Asset\nManagement Company total U$5 billion AUM in Asia\nincluding SICAV & hedge funds, private equity funds, real\nestate funds and approximately US$120 billion AUM\nworldwide.\nPosition Held: Head of Finance, Asia July’11 to July’15\nFinance and Admin Manager Dec’05 to July’11\nJob Description: 1. Reporting to Managing Director of Asia Pacific and\ndotted line to Head of Group Finance in London,\noverseeing all accounting and financial / management\nreporting functions in Asia pacific including Singapore,\nHong Kong, China, Australia, Japan and Indian offices.\n2. As Asia Senior Management team (AMT) member,\nattending regular AMT and board meetings to report\nfinancial performance of Asia Pacific region, provide\nfinancial input to Asia strategy, evaluate organic and M&A\nopportunities from finance perspective and participate in all\ncorporate development initiatives in the region.\n3. Holding directorship in portfolio company in Henderson\nPrivate Equity Fund HAPPII (US$250m) from 2012 to\n2015 , attending investment committee meetings, quarterly\ninvestors’ meetings, fund performance reporting. Review\nChina investment’s return and risks, discussion of exit\nopportunities with various parties.\n4. Working with private equity team and direct property\n(real estate ) team in private equity and real estate fund\nstructure set up, providing input on tax incentive and\nimplications etc\n5. Ensure statutory and regulatory obligations are met in\nrespect of preparation and filings of all statutory and\nregulatory reports in Asia pacific region, experienced in\nliaisons with MAS Singapore, SFC HK, FSA Japan, ASIC\nAustralia and AIC China. Experienced in preparing and\nreviewing regulatory reports including but not limited to\nthe following:\n-Singapore MAS quarterly forms and Income &\nExpenditure reports\n- Singapore MAS annual financial return and AUM surveys\n- Singapore Statistical Board quarterly AUM surveys\n- Singapore ACRA financial statements filings\n- HongKong FRR returns\n- Australia annual financial returns\n- Japan quarterly FSA reports\n- China MOF / AIC monthly, quarterly and annual reports\n6. Supervising two direct reports (Senior FM & Accounting\nManager) in Singapore hub plus two local financial\ncontrollers in Japan and Australia to ensure timely, accurate\nand presentable financial reports and deliverables for all\nAsia Pacific entities.\n7. Review and present management reports and monthly\nfinancial package for Asia pacific region to AMT and\nLondon headquarter on monthly basis.\n8. In charge of consolidated Strategic Plan and consolidated\nannual budget / forecast preparation for Asia Pacific region.\n9. Liaison with UK group finance team / management\ninformation team / tax team in respect of inter-company\nissues, transfer pricing and group reporting requirements.\n10. Liaison with external auditors in the region on statutory\naudit and tax consultants on corporate tax / indirect tax\ncalculation and filings.\n11.Review and streamline accounting practice and\naccounting policies in Asia Pacific to ensure both group\nand local requirements are met\nCompany: Siemens Medical Instrument Pte Ltd\nFrom Jan’05 to Dec’05\nNature of the firm: German Manufacturing company listed in NYSE with\nannual turnover of S$240million contributed from\nSingapore medical division.\nPosition Held: Senior Accountant\nJob Description: 1. Provide KPI analysis for factory performance control\nand profit and loss analysis for ESPRIT reporting, mainly\n❖ Delivery time& Delinquent backlog\n❖ Manufacturing cycle time\n❖ Rolled throughput yield\n❖ Inventory turnover\n❖ EBIT and Operating Cash Flow analysis v.s\nprior period and budget\n2. In Charge of US Sarbanes-Oxley Act compliance work\nand other internal control assessments according to\nSiemens internal audit requirement.\n• Documentation of SOX control activities ( Siemens\nAnnex 2 and Annex 3 preparation)\n• Lead testing team of 12 members to conduct\ninternal testing\n• Evaluation of deficiencies and implementation of\nremediation actions\n3. Monitor and refine web-based Transfer Pricing\nManagement System (TPMS) and provide monthly pricing\nanalysis by major products and customers\n4. Co-ordinate FY05/06 sales budget and preparation of\nmaster budget according to Siemens budget premise.\nCompany: ITT Industries (Singapore) Pte Ltd.\n(A Subsidiary of ITT Industries Inc)\nFrom Dec’99 to Dec’04\nNature of the firm: Manufacturing and Regional Headquarter of Electronics\nComponents Division of ITT Industries Inc, a US Multi-\nnational Company with $6 billion annual turnover\nPosition Held: Assistant Finance Manager Jan’04 to Dec’04\nSenior Financial Analyst July’01 to Dec’03\nFinancial Reporting Analyst Dec’99 to July’01\nJob Description: 1. In charge of the group financial reporting and analysis\nfunction with overall responsibility in consolidation,\nfinancial result analysis and preparation of monthly\nfinancial reporting package for Asia Pacific region.\n2. Review and consolidation of Asia Pacific group\nmanagement accounts (altogether 9 entities) according\nto US GAAP & review of China and HongKong\nsubsidiaries’ financial accounts.\n3. Conduct monthly business risk and opportunity\nanalysis, co-ordination of yearly strategic plan,\noperating plan and budget for the whole group.\n4. Review and provide guidance on accounting, costing\nand internal control functions in regional units, assisting\nfinancial controller in preparation of monthly Controller\nLetter .\n5. Responsible for US Sarbane-Oxley Act (SOX)\ncompliance in Singapore HQ, leading a cross-function\nSOX team to improve internal control process in\nrevenue, purchase, inventory, fixed assets, payroll\ncycles. Perform SOX audit with ITT internal auditor\nPwC in China companies\n6. Supervision 3 staff in the team.\nCompany: Morison International\nCertified Public Accountants, Singapore\nFrom Dec’97 - Nov'99\nNature of the firm: Accounting and auditing firm\nJob Description: Audit junior to Senior\n1) Independent local and overseas audit on full set of\naccounts including Manufacturing, Construction,\nTrading, Investment holding, Shipping, Jewelry, Travel\nagency and Logistic companies.\n2) Special audit on client's internal control system, GST\ncompliance and preparation of walkthrough flowcharts\n& management letters for control improvement.\n3) Consolidation of financial accounts and review of\nclient's financial management reports.\n4) Liaison with clients on statutory audit and internal\ncontrol issues.\n5) Due diligence work for overseas construction company\nto apply syndicated loan from USA\n6) Supervising a team of audit assistants and reviewing\ntheir audit works\nCompany: Shanghai Lansheng - Daewoo Co., Ltd\nAug'96 - Nov'97\nNature of the firm: Joint venture between Korean MNC and Shanghai listed\nCo. in international trading business with annual turnover\nof US$0.5 billion\nJob Description: Financial Accountant\nIn charge of Accounts receivable function and debtors'\naging analysis\nFinancial analysis on management reports and cash flow\nforecasting\nCOMPUTER SKILLS:\n• Proficient in Ms Office software\n• Working Knowledge of Hyperion, MAPICS (ERP) system,\nCODA system.\n• knowledge of SAP GL, AP module.\nHOBBIES: Swimming, jogging, martial art (Taiji) Reading and Writing\nLANGUAGE SKILLS: Fluent in English, Mandarin (mother tongue)\n",
    "skills": [
      "accounting",
      "finance"
    ],
    "experience": 20,
    "education": [
      "EDUCATION: MBA in Finance with Distinction",
      "Published Research Paper <Electronics: A case study of",
      "Economic Value Added in Target Costing> in Academic",
      "Bachelor of Economics (International Accounting)",
      "QUALIFICATION: Fellow member of Association of Chartered Certified",
      "Accountant (ACCA), UK",
      "ACCA Worldwide Prize Winner (1993)",
      "tax reporting of the Master-Feeder Fund and its 10 SPVs",
      "quarterly investor report to LPs and assist in calculations of",
      "3. Responsible for investor capital calls, distribution,",
      "investment exit repayment, management fee calculation",
      "5. Managing cash flow of the fund and its SPVs, maintain",
      "Master-Feeder Fund and SPV bank accounts to ensure",
      "efficient cash management and proper internal control",
      "declaration for MAS S13X & S13R as well as FATCA and",
      "CRS return filing for the Master-Feeder Fund and SPVs,",
      "investment exit in terms of Gross /net IRR calculation,",
      "2. Managing cash flow and act as the bank authorized signer",
      "returns and assist in ECI and PIC calculations",
      "including SICAV & hedge funds, private equity funds, real",
      "implications etc",
      "- Singapore Statistical Board quarterly AUM surveys",
      "Manager) in Singapore hub plus two local financial",
      "annual budget / forecast preparation for Asia Pacific region.",
      "calculation and filings.",
      "and local requirements are met",
      "Company: Siemens Medical Instrument Pte Ltd",
      "Singapore medical division.",
      "❖ EBIT and Operating Cash Flow analysis v.s",
      "master budget according to Siemens budget premise.",
      "1) Independent local and overseas audit on full set of",
      "to apply syndicated loan from USA",
      "Financial analysis on management reports and cash flow",
      "forecasting"
    ],
    "personal_info": {
      "email": "gefang@singnet.com.sg",
      "phone": "65-94761969"
    },
    "timestamp": "2025-06-12T11:11:55.734371"
  },
  {
    "file_path": "C:\\Users\\vasis\\Downloads\\resumeData\\eFinancialCareers_TT - CV.pdf",
    "name": "Trisa Tay, Chartered Accountant (Ca)",
    "raw_text": "TRISA TAY, CHARTERED ACCOUNTANT (CA)\n46B Toh Tuck Road #05-06 Singapore 596748\n(65) 9889 0012\ntrisa_tay@yahoo.com\nA Chartered Accountant trained in Big 4 Accountancy firm, with over 20 years of experience\nas Financial Controller. Expert in financial & regulatory reporting, fiscal management and\naccounting system development.\nProven record in compliance and risk management, developing and implementing\noperational and financial controls that meets regulatory requirements and improved the\nbottomline. High level of IT literacy including Advanced Excel skills; and the ability to adapt\nto many different environments.\nPROFESSIONAL EXPERIENCE\n2007 to Present\n(Private Equity)\nZANA CAPITAL PTE LTD Aug 2009 to Present\n(investment and support team of CMIA novated to current company)\nFinancial Controller\nCMIA CAPITAL PARTNERS PTE LTD Jan 2007 to Jul 2009\nFinancial Controller\nKEY RESPONSIBILITIES\nLeadership\n• Act as a positive representative for company Finance with\nbusiness stakeholders.\n• Investor relations liaison.\n• Report to CEO and COO.\nCompliance & Risk Management\n• Chief Compliance Officer overseeing entire compliance function\nincluding AML, Sanctions, Frameworks and Regulatory matters.\n• Liaise with the governing and licensing authorities: Monetary\nAuthorities of Singapore (“MAS”), the Economic Development\nBoard of Singapore (“EDB), and SPRING Singapore.\n• Regulatory Reporting to MAS, EDB, SPRING Singapore, IRAS\nand ACRA.\n• Supervise investment guidelines monitoring / restriction.\n• Capital management for regulatory purposes.\n• Ensure company is kept abreast of relevant regulatory and best\npractices development.\n• Provide compliance advice on business initiatives.\n• Review marketing materials for investment products.\n• Provide compliance training to improve confidence and\ncompetence of employees, and manage ad-hoc compliance\nrelated tasks.\n• Authority in AML/KYC, FATCA, CRS and Dodd-Frank.\n• AML/KYC checks and reporting, Dodd-Frank, FATCA & CRS\nreporting.\n• Liaison with Rating Agency (Mercer) to ensure the Singapore\nstructured funds meet Singapore regulatory criteria.\n• Presentation of risk findings and report to the Board of\nDirectors.\n• Business Continuity Plan documentation, and testing.\nTrisa Tay, CA\nOperations / Middle office\n• Deal Support, including legal documentation, corporate\nsecretarial documentation, financial modelling and deal\nstructuring.\n• Cash Management : prepare and review cash projections.\n• Capital calls, distributions, co-investments and carry interest\ncomputation and accrual.\n• Manage fund expenses and prepare annual budget.\n• Manage requests from investors, Investment Team, internal\nand external stakeholders.\n• Liaise with fund administrators, fund valuation service provider,\nbrokers, corporate secretaries, legal advisors and bankers.\n• Fund valuation.\n• Trade settlements with brokers and prompt filing with the\nrelevant Stock Exchanges (Singapore, Hong Kong, Germany).\n• SPV management\nBusiness Partnering\n• Financial Controller with full responsibility for the accounting,\ncompliance and operations of the funds and fund management\nCompany (AUM S$250 million).\n• Contributed to the successful award of Capital Markets\nServices Licence and Tax Incentive Schemes for the funds and\nfund manager.\n• Compliance & Risk Management\n• Reviews of governance, risk, financial performance for\ninvestments.\n• Directed financial planning and analysis, key reporting\nprocesses, forecasting/budgeting, tax, treasury, MIS and\nadministrative functions through a 3-person finance &\nadministration team.\n• Review and challenge investment valuation, NAV calculations,\nand carry calculations.\n• Perform daily cash flow.\n• Review documents and provide support on investments and\ndivestments of the Funds.\n• Singapore subject matter expert – Monetary Authority of\nSingapore (“MAS”) regulations and reporting, IRAS, Goods and\nServices Tax, ACRA submission etc.\n• Impact merger and acquisition decisions - Financial due\ndiligence and Financial modeling.\n• Shared service centre – provide reporting and analysis services\nto Investments team. Tailor reports to business unit\nrequirements.\n• Effective interaction with shareholders whilst appreciating their\nnon-financial background.\nFinancial Control.\n• Start-up Zana Capital Pte Ltd with successful exempt licence\napplication. Subsequently successfully obtained Capital\nMarkets Services (“CMS”) Licence\n• Remote control of Shanghai subsidiary.\n• Successful fund launches in Cayman Islands and Singapore.\n• Management & statutory reporting in IFRS and US GAAP for\nFunds, SPVs and Fund Manager.\nTrisa Tay, CA\n• Consolidation of management accounts of Singapore and\nShanghai subsidiary.\n• Tax planning for Singapore, Shanghai offices, and Funds.\n• Budgeting management and forecast\n• Cash management.\n• Best practices - Process improvement measures.\n• Quarterly Fund Report to investors.\n• Presentation for financial decision-making to the Board of\nDirectors and Advisory Committee\n• Human Resource, payroll and administrative matters.\n• Corporate secretarial matters.\n• Led tax savings efforts for funds and co-investors.\no Saved over U$14 million in potential taxes through\naccounting and tax treatment in support of divestment\nSPVs.\n• Liaison with auditors, bankers, legal counsel, tax consultants\nand investors.\nAug to Dec 2006 RESOURCES GLOBAL PROFESSIONAL (SINGAPORE) PTE LTD\nFinance Associate (contract)\n• Assessed and developed key controls for inventory, accounts\npayable, accounts receivable and payroll systems of a US\nsubsidiary, MPV Asia (based in Malaysia), associate with\nSarbanes-Oxley Section 404 certification of internal control\nenvironment.\n• Internal audit testing for US subsidiary, International Flavours &\nFragrances Inc. Recommended improvements of controls for\nintercompany, tax, accounts payable and payroll processes.\nOct 2005 to Jul 2006 OPENWAY ASIA PTE LTD\nFinancial Control (contract)\n• Report to CEO, who is ex-CEO of VCHEQ.com.\n• Budgeting, Forecast, management and statutory reporting.\n• Contributed to savings of S$100,000 by effective tax appeal.\n• Tax planning for Thailand, Vietnam and Indonesia.\n2003 to Sep 2005 LIBERTY MUTUAL INSURANCE EUROPE LIMITED\nFinancial Controller\nBusiness Partnering\n• Contributed to the successful award of Tax Incentive Schemes\nfor the company.\n• Review business cases and ensure investment decisions are\nmade with clear understanding of their impact on net profits.\n• Work closely with and influence senior management to help\ndrive business performance.\n• Challenge revenue budget of the line managers via application\nof finance disciplines to decision making, such as Financial\nmodeling.\n• Funding and resource allocation - drive financial efficiency with\nTrisa Tay, CA\ndivisions with rigorous pressure on costs and a commitment to\nvalue-for-money approach.\n• Assessing risks to the delivery of business plans – formulate\nand drive actions to mitigate them.\n• Shared service centre – provide reporting and analysis services\nto Investments team. Tailor reports to business unit\nrequirements.\n• Manage corporate project budgets and performance.\n• Sharing best practices with Group CFOs on a quarterly basis.\n• Perform internal audit to counter-part office in Sydney and\nrecommended improvements in controls for business units and\nFinance department.\nDay-to-day\n• Start-up Finance & Administration Department.\n• Report to the Asia-Pacific CEO based in Sydney, with dotted-\nline reporting to the CFO based in Boston.\n• Management and statutory reporting in IFRS and US GAAP.\n• Tax, treasury, risk management.\n• Human resources, payroll, company secretarial and\nadministrative functions.\n• Implementation of Front-end ERP system and backend system\nin Singapore. First mover globally to utilise GST tax reporting,\ncheque printing and Fixed Assets module.\n• Consolidated accounting team to support Asia Pacific business.\n• Savings in 4 finance headcount, approximately S$250,000 per\nannum through the effective use of IT technology : 6 staff in\nAsia-Pacific office vs 2 staff in Singapore for the same revenue\nturnover.\n• Sarbanes-Oxley Section 404 certification of internal control\nenvironment.\n• Consolidated activities in tax\n• Saved over US$20 million in potential taxes through\nfinancial contract review for clients to bear withholding tax.\nMay 2000 to Dec 2002 VCHEQ,com PTE LTD\nFinancial Controller\nBusiness Partnering\n• Contribute to the successful award of EDB/IDA grant of S$3.7\nmillion.\n• Work closely with and influence senior management to help\ndrive business performance.\n• Obtained approval by the Board of Directors (consisting of\ninternational blue-chip investors) of the revenue plans, using\nFinancial Modelling of assumptions validated by the Sales\nTeam.\n• Review business cases and ensure investment decisions are\nmade with clear understanding of their impact on net profits.\n• Impact merger and acquisition decisions - provide Financial\ndue diligence and Financial modeling for a potential acquisition\nof company in Toronto, Canada.\n• Funding and resource allocation - drive financial efficiency with\ndivisions with rigorous pressure on costs and a commitment to\nTrisa Tay, CA\nvalue-for-money approach.\no Re-negotiated contract with service providers,\neliminating cost of sales by S$250k per annum.\n• Shared service centre – provide reporting and analysis services\nto Investments team. Tailor reports to business unit\nrequirements.\n• Assessing risks to the delivery of projects – formulate and drive\nactions to mitigate them.\n• Shareholder value analysis using ROI, ROC. Effective\ninteraction with shareholders whilst appreciating their non-\nfinancial background.\n• Manage project budgets and performance.\n• Investigate opportunities as well as high risk and material\nfinancial issues, or problem areas, with the business. Develop\nand propose solutions and options to resolve / progress\nconcerns to a satisfactory outcome\n• Develop Employee Stock Option Plan to retain staff.\nDay-to-day\n• Start-up Finance & Administration Department.\n• Management and statutory reporting in IFRS and US GAAP.\n• Tax, treasury, risk management.\n• Human resources, payroll, company secretarial and\nadministrative functions.\n• Handle investors queries with international investors like JP\nMorgan, Allianz AG, Government of Singapore Investment\nCorp. etc.\n• Efficient corporate tax structure, and contributed to savings in\npotential tax liability.\nEarlier Career :\nApr 1998 to Apr 2000 CHARTERED ASSET MANAGEMENT PTE LTD\nFinance & Administration Manager\n• Tax structuring for hedge fund based in Mauritius.\n• Director of the hedge fund.\n• Drive operational improvements.\n• Management and statutory reporting for Group (including\nMalaysia companies) in IFRS\n• Tax, treasury, risk management, Human Resource & payroll,\ncompany secretarial and administrative functions.\nMar 1996 to Mar 1998 ARTHUR ANDERSEN LLP\nManager, Client Accounting Services\n• Manage 15 staff to provide outsourced accounting in US GAAP\nand IFRS, payroll and GST submission services to clients.\n1995 to Feb 1996 L.N. GROUP OF COMPANIES\nTrisa Tay, CA\nFinance & Administration Manager\nAssist the CFO (former director of Neptune Orient Lines Limited)\nin :\n• Management and statutory reporting.\n• Budgeting, forecast and cashflow management\nMay 1988 to Dec1994 NEPTUNE ORIENT LINES LIMITED\nFinance & Administration Manager (IT Subsidiary, Trident\nInfotech Pte Ltd)\n• Start up Finance & Administration Department\n• Management and statutory reporting of Singapore and\nPhilippines office.\n• Budgeting, forecast and cashflow management\n• Tax, treasury, risk management, Human Resource & payroll,\ncompany secretarial and administrative functions.\nSenior Accountant, Group Budget\n• Consolidated the Group Budget and provide quarterly variance\nanalysis.\nJul 1986 to Apr 1988 PRICEWATERHOUSE LLP\nAudit Semi-Senior\n• Participated in numerous financial audits for organisations of\nvarious sizes, such as shipping companies, trading companies,\ninvestment banks, manufacturing companies etc.\nPROFESSIONAL AFFILIATION\nChartered Accountant\nICPAS\nEDUCATION\nBachelor of Accountancy\nNational University of Singapore\nPost-graduate Diploma in Human Resource Management\nSingapore Institute of Management\nIT SKILLS\nMicrosoft Excel, Word, Powerpoint, MYOB, Great Plains, ACCPAC, EasyPay and\nFixed Assets.\n",
    "skills": [
      "accounting",
      "ca",
      "excel",
      "finance",
      "leadership"
    ],
    "experience": 20,
    "education": [
      "TRISA TAY, CHARTERED ACCOUNTANT (CA)",
      "as Financial Controller. Expert in financial & regulatory reporting, fiscal management and",
      "ZANA CAPITAL PTE LTD Aug 2009 to Present",
      "CMIA CAPITAL PARTNERS PTE LTD Jan 2007 to Jul 2009",
      "• Capital management for regulatory purposes.",
      "• Authority in AML/KYC, FATCA, CRS and Dodd-Frank.",
      "• AML/KYC checks and reporting, Dodd-Frank, FATCA & CRS",
      "Trisa Tay, CA",
      "• Cash Management : prepare and review cash projections.",
      "• Capital calls, distributions, co-investments and carry interest",
      "• Contributed to the successful award of Capital Markets",
      "processes, forecasting/budgeting, tax, treasury, MIS and",
      "• Review and challenge investment valuation, NAV calculations,",
      "and carry calculations.",
      "• Perform daily cash flow.",
      "• Start-up Zana Capital Pte Ltd with successful exempt licence",
      "application. Subsequently successfully obtained Capital",
      "• Successful fund launches in Cayman Islands and Singapore.",
      "Trisa Tay, CA",
      "• Budgeting management and forecast",
      "• Cash management.",
      "Sarbanes-Oxley Section 404 certification of internal control",
      "• Budgeting, Forecast, management and statutory reporting.",
      "• Review business cases and ensure investment decisions are",
      "• Challenge revenue budget of the line managers via application",
      "• Funding and resource allocation - drive financial efficiency with",
      "Trisa Tay, CA",
      "• Sarbanes-Oxley Section 404 certification of internal control",
      "• Review business cases and ensure investment decisions are",
      "of company in Toronto, Canada.",
      "• Funding and resource allocation - drive financial efficiency with",
      "Trisa Tay, CA",
      "Earlier Career :",
      "Trisa Tay, CA",
      "• Budgeting, forecast and cashflow management",
      "• Budgeting, forecast and cashflow management",
      "EDUCATION",
      "Bachelor of Accountancy"
    ],
    "personal_info": {
      "email": "trisa_tay@yahoo.com",
      "phone": ""
    },
    "timestamp": "2025-06-12T11:11:56.152643"
  },
  {
    "file_path": "C:\\Users\\vasis\\Downloads\\resumeData\\Lion Global_Ivy Choo_Investment Compliance Assistant Manager.pdf",
    "name": "Choo Gui Yi, Ivy",
    "raw_text": "Choo Gui Yi, Ivy\nAddress: 38 Lorong N Telok Kurau #04-04 S(425163)\nDOB: 12 September 1986\nGender: Female\nCitizenship: Singaporean\nRace: Chinese\nMarital Status: Married\nMobile: +65 97954868\nEmail: ivycgy@yahoo.com.sg\nWork History & Responsibilities\n1. Company: Lion Global Investors Limited\n• Duration: October 2012 to Present\n• Position: Assistant Manager, Investment Compliance\n• Job description:\n- Monitor investment activities and implement controls to ensure company’s\npolicies and guidelines are adhered to.\n- Ensure compliance with investment guidelines, setting up and maintain rules in\nBloomberg AIM.\n- Provide advisory on investment/regulatory guidelines and rule coding with regard\nto new and existing mandates.\n- Investigate trade breaches and follow-up with fund managers to ensure\nrectification within approved timeline.\n- Carry out daily trade approval and reporting.\n- Prepare scheduled reports according to the relevant investment guidelines.\n- Attend to compliance enquiries from investment team.\n- Provide investment compliance training to the investment team.\n- Carry out projects on enhancement of compliance processes on ad-hoc basis.\n2. Company: Conocophillips Asia Ventures Pte Ltd\n• Duration: March 2012 to October 2012\n• Position Held: Compliance Analyst (Contract)\n• Job description:\n- Ensure consistent execution of policies and procedures as part of global\nCompliance team.\n- Assist with the group business continuity planning and testing\n- Trade floor presence to monitor trading activities against various policies.\n- Carry out investigations upon receipt of alerts for trade violations from the\ntransaction monitoring team.\n- Support daily process which enables traders to confirm the accuracy of their deals.\nPage 1 of 3\nChoo Gui Yi, Ivy\n- Support the counterparty approval process by conducting appropriate due\ndiligence on potential new trading counterparties.\n- Provide advisory and compliance support to the trading floor.\n3. Company: Bank of China\n• Duration: April 2011 to March 2012\n• Position Held: Compliance Officer (Retail Banking)\n• Job description:\n- Assist in performing compliance monitoring and reviews.\n- Provide advisory for KYC issues and compliance support to business units.\n- Conduct inspection; generate report on findings and recommendations.\n- Prepare compliance checklist and assist in training on AML issues.\n- Review and revise policies, assure that the functions’ policies and standards\nrelating to regulatory compliance are effectively implemented.\n- Dissemination of information relating any change in regulation, AML/CFT update\nand any other information from Legal & Compliance Department to business\nunits.\n4. Company: CIMB Bank Berhad\n• Duration: January 2010 to December 2010\n• Position Last Held: Account Services Executive\n• Job description:\n- Assess customer profile and documents to ensure compliance of bank policy and\nMAS626 before approval of account opening and reports.\n- Authorise updates of customer details, ensure accuracy and verification of\ncustomers’ identity.\n- Supervise officers on daily operations; consistently ensure accuracy on account\nmaintenance.\n- Liaise with Risk Management for project on operational risks, review current\nwork processes and propose risks controls.\n- Liaise with project management team on evaluation of officers’ productivity and\ndaily volume of work load.\n- Train new staff on Individual and Corporate account openings.\nPage 2 of 3\nChoo Gui Yi, Ivy\nEducation Summary\n• Aug 2006 - Jun 2009 – University of London (SIM), Singapore\nBSC of Science (Business), 2nd Class upper honours\n• Jan 2003 - Dec 2004 – Serangoon Junior College (SRJC)\nGCE ‘A’ level 3 credits\n• Jan 1999 - Dec 2002 – Tampines Secondary (TPSS)\nGCE ‘O’ level 7 credits\nProfessional courses attended\n• Year 2014: Certificate in Fund Administration\n• Year 2012: Bloomberg AIM\nSkills\n• English and Chinese (Written and Spoken)\n• MS Office, Excel and Powerpoint\n• Bloomberg (AIM)\nPersonality\n• Eager to learn and seek self-improvement\n• Proactive and team player\nPage 3 of 3\n",
    "skills": [
      "excel"
    ],
    "experience": 0,
    "education": [
      "rectification within approved timeline.",
      "- Carry out daily trade approval and reporting.",
      "- Carry out projects on enhancement of compliance processes on ad-hoc basis.",
      "- Carry out investigations upon receipt of alerts for trade violations from the",
      "- Authorise updates of customer details, ensure accuracy and verification of",
      "Education Summary",
      "• Year 2014: Certificate in Fund Administration"
    ],
    "personal_info": {
      "email": "ivycgy@yahoo.com.sg",
      "phone": "+65 97954868"
    },
    "timestamp": "2025-06-12T11:11:56.338846"
  },
  {
    "file_path": "C:\\Users\\vasis\\Downloads\\resumeData\\LT CV 201608.pdf",
    "name": "Personal Particulars",
    "raw_text": "PERSONAL PARTICULARS\nName: Lee Li Ting\nContact: 9876 1091 (mobile); ltlee74@gmail.com (e-mail)\nGender: Female\nNationality: Singaporean\nCurrent salary: $14,000/month\nAge: 42\nMarital status: Married\nWORKING EXPERIENCE\n2007 – Present\nEDBI Pte Ltd/ EDB Investments Pte Ltd/ Bio*One Capital Pte Ltd\n– Director, Finance (2015 - Present)\n– Deputy Director, Finance (2012 - 2015)\n– Associate Director, Finance (2009 - 2012)\n– Finance Manager (2007 - 2009)\nAchievement: Attainment of tax incentives for fund companies and implementation of\njob rotation within finance department\nResponsibilities:\n• Manage a finance team of six (1 senior manager, 2 managers and 3 senior\nofficers)\n• Oversee the finance operations of 2 fund managers and 13 fund companies with\nmore than 200 investees\n• Ensure accurate and timely monthly, quarterly and year-end reports (including\ngroup consolidation and financial performance of fund companies) to stakeholders\n• Directorship of 10 fund companies\n• Provide inputs on divestment and investment matters\n• Review of finance policies and procedures and ensure financial operations are in\ncompliance with group policies and processes\n• Oversee group tax planning and review tax computation and GST submission\n• Review annual budget and quarterly forecast to stakeholders\n• Manage and review capital call and redemption processes\n• Review transactions and journal entries to ensure accuracy and appropriate\nsupport documentation\n• Liaise with auditors (both external and internal) on annual audit, bankers on\ntreasury, corporate secretary and statutory authorities on statutory matters\n• Oversee upgrade of accounting system and data migration of investment software\n2000 – 2007\nGreif Singapore Pte Ltd – Accountant\nResponsibilities:\n• Supervise a team of three finance executives/ assistants\n• Perform:\no Standard costing reviews and analysis\no Annual budget review\no Management of tax matters, including GST\no Preparation of head office report package\no Management of company’s secretarial matters\no Liaise with auditors, bankers, lawyers and statutory authorities\no Cash flow management\no Monitoring of inter-company transactions\n• Prepare, review and analyze financial performance of company’s operations in\nSoutheast Asia\n• Involve in upgrading of accounting system\n• Ensure SOX compliance of the company\n• Appointed as SOX auditor to perform SOX audit for associate companies in\nChina\n• Impart accounting knowledge and advise associate companies in China on US\nGAAP\n• Involve in implementation of ERP system (BPCS) for associate companies in\nChina\n1997-2000\nRotol Singapore Ltd – Accountant\nResponsibilities:\n• Supervise a team of six finance executives/ assistants\n• Perform:\no Company’s financial result review and analysis\no Liaising with auditors, bankers, company secretary, tax and statutory\nauthorities for negotiation and management of treasury, statutory and tax\nmatters\no Cash flow management\no Preparation and monitoring trade financing\no Intercompany transactions monitoring\no Translation of accounts\n• Involve in implementation of ERP system\n• Assist in applications for Investment Allowance\nMay 95 – Jul 95\nK H Chia & Co – Trainee\n• Assisted seniors in audit, account and income tax jobs\nJan 93 – Jun 93\nInland Revenue Authority of Singapore – Tax Assistant\n• Assist supervisor in review of income tax and perform clerical work\nPROFESSIONAL QUALIFICATION\nCA (Singapore) 2013 - Institute of Singapore Chartered Accountants\nCPA 2000 - Institute of Certified Public Accountants of Singapore\nEDUCATION\nBachelor of Accountancy 1996 - Nanyang Technological University\nGCE “A” level 1992 - St Andrew’s Junior College\nGCE “O’ Level 1990 - Crescent Girls’ School\nSOFTWARE SKILLS\nMS Office: Word, Excel and PowerPoint\nAccpac\nTelmera: Access Database\nHyperion and HFM\nNOTICE PERIOD\n3 months\n",
    "skills": [
      "accounting",
      "ca",
      "excel",
      "finance"
    ],
    "experience": 0,
    "education": [
      "EDBI Pte Ltd/ EDB Investments Pte Ltd/ Bio*One Capital Pte Ltd",
      "• Review annual budget and quarterly forecast to stakeholders",
      "• Manage and review capital call and redemption processes",
      "o Cash flow management",
      "o Cash flow management",
      "• Assist in applications for Investment Allowance",
      "• Assist supervisor in review of income tax and perform clerical work",
      "PROFESSIONAL QUALIFICATION",
      "CA (Singapore) 2013 - Institute of Singapore Chartered Accountants",
      "EDUCATION",
      "Bachelor of Accountancy 1996 - Nanyang Technological University"
    ],
    "personal_info": {
      "email": "ltlee74@gmail.com",
      "phone": "2012 - 2015"
    },
    "timestamp": "2025-06-12T11:11:56.496561"
  },
  {
    "file_path": "C:\\Users\\vasis\\Downloads\\resumeData\\Luminance Fund_Saleem Lalani_Research Associate.pdf",
    "name": "Saleem Lalani",
    "raw_text": "SALEEM LALANI\nLinkedIn: https://sg.linkedin.com/in/saleemlalani\nSkype: saleemlalani Mobile: +65 98 64 00 30 Email: saleem.lalani@gmail.com\nCAREER SYNOPSIS:\n Corporate finance professional with experience in M&A, Private equity advisory, Consulting & Restructuring in Asia and the Middle East.\n Track record of building on: transaction experience, market knowledge, pro-active collaboration with other departments to generate ‘new\nideas/ opportunities’ for the team.\n Consistently developed effective relationships: 1) Multinational corporations and regional business groups; 2) Sovereign wealth funds,\nprivate equity - VC firms and Family offices; 3) Government agencies and international development institutions\n Good knowledge and commercial understanding of major sectors: technology and e-commerce, logistics and distribution, consumer goods,\nF&B, retail, leisure and hospitality, engineering & construction and energy & power.\n Significant experience in financial modelling, due diligence, debt & CAPEX review, transaction structuring, preparing deal documents,\ncrafting presentations and pitch/proposals, client relationship management, data room management and investor readiness.\n Actively used major research portals: Capital IQ, Thomson Reuters, Bloomberg, Merger Market and One Source.\n Well versed with client onboarding, KYC, compliance, legal-documentation, coordination with auditors, lawyers and regulators (SEC).\nPROFESSIONAL EXPERIENCE:\nLUMINANCE FUND (Swiss-Asia Financial Services) – Part-Time Research Associate: (December 2016 – to date) – Singapore\nResearch, company peer-analysis, preparing briefs: on quarterly results and calls with IR department of listed companies (India and ASEAN)\nCONSULTANT / MENTOR: (November 2015 – to date) – Singapore\n Assisting companies and entrepreneurs on ‘investor-JV partner’ search and market entry strategy in F&B and Tech-driven businesses.\nMentoring start-ups from www.jfdi.Asia , Infocomm Investments ( www.catch.com.sg ) and muru-D ( www.freightkart.com )\nIFC (WORLD BANK) – Short Term Consultant - Singapore (August – September 2015)\nPrivate sector investment mobilization project. Identifying and engaging: global and regional blue chips as well as major Singaporean\ncompanies involved in agriculture, food processing, logistics and infrastructure value chains. Developed value chain analysis, pitch documents\nand workshop material for engaging the private sector and the government.\nENVESTORS MENA – UAE (May 2014 – July 2015) – Relocated to ASEAN\nDeveloped financial projections and investor presentations. Drafted LOIs and Term Sheets. Conducted business performance reviews and\nworking capital/debt analysis. Researched and developed detailed lists of potential investors and companies. Key Transactions:\n Equity Raise and Strategic Advisory: Fitness and Wellness Company (US$ 5 mn) - 2015\n Equity Raise: Brokerage Management Technology Solutions Company (US$ 5 mn) - 2015\n Project Funding: Dinner Theatre Project (US$ 10 mn) - 2014\nOUTLOOK ADVISER, UAE - (March 2013 – April 2014)\nDeveloped financial models and investor presentations for equity and debt raising. Developed performance and management reporting\ntemplates. Worked with lawyers to develop investment holding company structure. Key Transactions:\n Financial and Business Advisory: Restaurant and Hospitality Business (US$ 25 mn) - 2014\n Financial and Business Advisory: Pharma OTC Business (US$ 20 mn) - 2013\nDELOITTE CORPORATE FINANCE (MIDDLE EAST) LIMITED – MANAGER (Mar 2009 – Dec 2012)\nExecuted advisory, business review, due diligence and debt restructuring engagements. Responsible for deal documentation, project\nmanagement, client relationship, risk management and compliance matters and ‘KYC’. Supported leadership team in origination. Led initiatives\nto develop sector knowledge, researching potential buyers and target companies. Drafted Term sheets and Offer letters. Key Transactions:\n Buy Side: Global Blue Chip Logistics Company (US$ 20 mn) - 2012\n Sell Side: Automation and Energy Management Solutions Company (US$ 20 mn) - 2011\n Business Review and Restructuring: Major Construction and Industrial Conglomerate in Abu Dhabi - 2010\n Sell Side: Process Controls Company to a Global Electronics Equipment Manufacturer (US$ 60 mn) - 2010\nSTART CONSULT, UAE – ASSOCIATE (Jan 2006 - Dec 2008)\nExecuted due diligence, corporate finance advisory, and business reviews. Developed financial model and investor presentations. Co-ordinated\ndue diligence (accounting and legal) and post-acquisition legal documentation process. Key Transactions:\n Advisory: LPG Terminal & Distribution Company, Pakistan (US$ 15 mn) - 2009\n Privatisation of Oil Marketing Company. Pakistan (US$ 1,500 mn) - 2007\nKPMG FINANCIAL ADVISORY SERVICES - ANALYST (Oct 2001 - Dec 2005)\nCarried out financial analysis and industry research. Supported managers and directors in developing due diligence reports, offer for sale\ndocuments, feasibility studies and responding to queries from Stock Exchanges and Securities and Exchange Commission (SEC)\nEDUCATION:\n Chartered Institute of Management Accountants (CIMA, UK) (2004)\n Bachelors of Commerce (B.Com) – University of Karachi (1999)\n Learned Mandarin language – Basic level (Jan 2013)\nPage 1 of 1\nSALEEM LALANI\nDeal Sheet\n Equity Raise: Fitness and Wellness Company (US$ 5 mn) - 2015\nLed the development of the financial plan and investor presentation. Assessed debt options. Helped client develop ‘new service\nlines’. Drafted LOI for new offerings/partnerships. Providing inputs on the legal and corporate structure. Identified and introduced\npotential investors. Identified sites for new studios.\n Equity Raise: Brokerage Management Technology Solutions Company (US$ 5 mn) - 2015\nProvided critical inputs to the client on financial and business plan. Helped develop Q&A document to articulate key\nUSPs/competitive advantages of a ‘complicated product-solution’. Identified and approached potential investors including based in\nthe USA, Europe and Asia. Introduced a potential COO and a major potential customer.\n Project Funding: Dinner Theatre Project (US$ 10 mn) - 2014\nDeveloped financial model and investor presentation. Articulated USPs: offtake agreements, advance ticket sales and ‘sweet spot’ in\nthe crowded sector. Developed and analysed potential deal structures with founders’ incentives. Provided introductions to potential\nvendors: concierge companies and hotel groups. Identifying and introducing potential investors.\n Financial and Business Advisory: Restaurant Company & Proposed F&B Fund - 2014\nDeveloped financial model and investor presentation for restaurant expansion. Identified corporate governance and management\nreporting improvements. Developed KPIs for outsourcing the operations.\nDeveloped ‘pitch book-investor presentation’ for a proposed F&B sector fund. Worked with lawyers to develop investment holding\ncompany structure.\n Financial and Business Advisory: Pharma OTC Business (US$ 20 mn) - 2013\nDeveloped financial plan and investor presentation for a ‘hangover relief’ OTC distribution. Assisted the promoter in identifying\ndistributors for the GCC region. Assisted in negotiations with the principal vendor in the USA. Lined-up potential investors.\n Buy Side: Global Blue Chip Logistics Company (US$ 20 mn) - 2012\nDeveloped presentation on strategic options for regional expansion. Led market mapping and development of a comprehensive list\nof potential targets. Approached priority targets for initial discussions and solicited interest in selling. Developed a detailed report on\na selected target – assessed strategic fit, financial performance and potential synergies for discussions with client’s global M&A team.\nDrafted indicative offer letter. Participated and supported in negotiations.\n Business Review and Restructuring: Well-known Family Group based in Saudi Arabia - 2012\nLed the financial, commercial and operational reviews of a Group company focusing on revenue drivers, profit margin analysis,\ncapital expenditure, financial reporting, bottlenecks for growth (operational, capital and human resource), and management\nreporting structures. Developed a report covering key findings and recommendations. Implemented a customized management\nreporting template.\n Sell Side: Automation and Energy Management Solutions Company (US$ 20 mn) - 2011\nOriginated the deal. Developed the information memorandum. Approached global strategic players and international PE firms.\nInitiated discussions with buyers’ corporate development/M&A teams, facilitated management meetings and Q&A sessions for\npotential buyers.\n Sell Side: Process Controls Company to a Global Electronics Equipment Manufacturer (US$ 60 mn) - 2010\nDeveloped the winning pitch and deal documents. Co-ordinated buyer’s due diligence and Q&A process. Participated in SPA and\nprice negotiations. Provided support with ad-hoc analysis during negotiations. As a team member helped increase the shareholder\nproceeds by c. 30% through robust project management, maintaining competitive tension and undertaking analysis to support price\nexpectations. Facilitated completion process with auditors and lawyers.\n Financial Advisory: LPG Terminal & Distribution Company (US$ 15 mn) - 2009\nDeveloped due diligence and strategic analysis report. Revised client’s financial projections based on the analysis.\n Privatisation of Oil Marketing Company (US$ 1,500 mn) - 2007\nWorked with McKinsey & Co, London office. Conducted commercial due diligence and financial and strategic analysis. Identified\ncompany’s competitive strengths and growth opportunities that had significant value creation opportunities.\n Anchor Transaction, Logistics Sector Private Equity Fund (US$ 100 mn) - 2007\nDeveloped financial model and investor presentation. Co-ordinated due diligence (accounting and legal), legal structuring and\nmanaged post-acquisition legal documentation process. Developed post-acquisition 100-day plan.\n Privatisation of State Owned Entities (multiple transactions) – 2004\nAssisted in preparation of Offer for Sale documents, coordinated with Securities and Exchange Commission (SEC) regarding review of\ndocuments, information requests and resolution of queries.\nSaleem Lalani – Deal Sheet Page 1 of 1\n",
    "skills": [
      "accounting",
      "finance",
      "leadership"
    ],
    "experience": 0,
    "education": [
      "CAREER SYNOPSIS:",
      " Significant experience in financial modelling, due diligence, debt & CAPEX review, transaction structuring, preparing deal documents,",
      " Actively used major research portals: Capital IQ, Thomson Reuters, Bloomberg, Merger Market and One Source.",
      "Research, company peer-analysis, preparing briefs: on quarterly results and calls with IR department of listed companies (India and ASEAN)",
      "Mentoring start-ups from www.jfdi.Asia , Infocomm Investments ( www.catch.com.sg ) and muru-D ( www.freightkart.com )",
      "ENVESTORS MENA – UAE (May 2014 – July 2015) – Relocated to ASEAN",
      "working capital/debt analysis. Researched and developed detailed lists of potential investors and companies. Key Transactions:",
      "Carried out financial analysis and industry research. Supported managers and directors in developing due diligence reports, offer for sale",
      "EDUCATION:",
      " Bachelors of Commerce (B.Com) – University of Karachi (1999)",
      "Provided critical inputs to the client on financial and business plan. Helped develop Q&A document to articulate key",
      "USPs/competitive advantages of a ‘complicated product-solution’. Identified and approached potential investors including based in",
      "Drafted indicative offer letter. Participated and supported in negotiations.",
      "capital expenditure, financial reporting, bottlenecks for growth (operational, capital and human resource), and management",
      "company’s competitive strengths and growth opportunities that had significant value creation opportunities."
    ],
    "personal_info": {
      "email": "saleem.lalani@gmail.com",
      "phone": "+65 98 64 00 30"
    },
    "timestamp": "2025-06-12T11:11:56.785585"
  },
  {
    "file_path": "C:\\Users\\vasis\\Downloads\\resumeData\\PWC_Olivia Peter_Regulatory Manager.pdf",
    "name": "Curriculum Vitae Oliviakarinapeter(Ms)",
    "raw_text": "Curriculum Vitae OliviaKarinaPeter(Ms)\nMobile:+6584069099\nEmail:oliviapeter@hotmail.com\nBackground\n Regulatory compliance specialist, particularly in the area of Anti-Money Laundering and\nCountering Financing of Terrorism (AML/CFT) and regulations for banks and capital\nmarketsserviceslicenceholders.\n Over6yearsofexperienceauditingfinancialinstitutionsinSingaporeandNewZealandand\ncurrentlyspecialisesinprovidingregulatorycomplianceadvisoryservices.\n Developed strong project management and communication skills through the planning and\ncoordination of audits with various stakeholders in order to produce multiple deliverables\nwithintightdeadlines.\nEducation\n BachelorsofAccounting(Hons)fromNanyangTechnologicalUniversity(Singapore)\n MemberofCertifiedPractisingAccountantsofAustralia(“CPAAustralia”)\nProfessionalExperiences\nManager Dec2014topresent\nRegulatoryAdvisoryServices\nPricewaterhouseCoopersRiskServicesPte.Ltd.,Singapore\n SubjectMatterExpert(“SME”)forateamof30staffperformingclientduediligencereviews\nfor a Swiss bank undergoing acquisition. The scope included the review of 400+ high risk\naccounts within 6 weeks and required coordination and communication with various\nstakeholders in both the acquirer and target banks. This included tabling of risks associated\nwithaccountsaswellasmitigatingfactorstoseniormanagementfortheirdecisionmaking.\n Subject Matter Expert (“SME”) and Team Leader for a KYC remediation project. Assisted a\nBritish bank in performing a one-off ‘back-book’ file review and remediation exercise for\nHong Kong and Singapore booked and/or managed client accounts (approximately 4,300\naccounts in total). Aspects of the file review and remediation processing included among\nothers, the assessment of the risk rating of the Bank’s clients, performing a gap analysis of\ntheKYC,performingadversenewschecks,transactionreviewsandtheprofilingoftheBank’s\nclientssourceofwealthwiththeassistanceofthebankers.\n Provided annual regulatory audit support and assessed clients’ compliance to Anti-Money\nLaundering Guidelines and regulators expectations for PwC’s bank clients as part of their\nreporting to the Monetary Authority of Singapore. For the gaps identified, provide\nrecommendations based on our experience/understanding of the local regulator’s\nexpectations and industry practices. PwC’s bank clients include retail, commercial and\nprivatebankinginstitutions.\n Performed gap analysis and recommended enhancements to a foreign bank's wire transfer\npoliciesandproceduresinlinewithSingaporeregulationsandindustrystandards.\n Conductedinternal AMLtrainingsfortheassurancedepartment\nSeniorAssociate Nov2013toNov2014\nFinancialServices\nPricewaterhouseCoopers(“PwC”)NewZealand,AucklandOffice\n Understandingandevaluatingclient’sbusinessprocessesandformulatingtheauditplan\nbasedontheassessedriskswiththegoaltoincreaseauditefficiency.\n LiaisingwiththevariouslinesofserviceswithinthefirmandthePwCinternationalnetwork\naswellastheclientsfinanceteam.\n Reviewofcapitaladequacycalculationsanddisclosurestoensureitscompliancewiththe\ncapitaladequacyframeworkasmandatedbytheReserveBankofNewZealand.\n Preparationofauditreportsthatwerepresentedtotheauditcommitteeandmanagement.\n KeyclientsincludeASBBankingGroup(ASBBank,CBAandtheASBmanagedfunds).\nAssistantManager Dec2009toNov2013\nFinancialServicesIndustryPractice\nPricewaterhouseCoopersLLP,Singapore\n Understandingandevaluatingclient’sbusinessprocesses(includingtheirdependencieson\nthesystemsandprocessesintheirHeadOffice)andformulatingtheauditplanbasedon\nthesefactors.\n Coordinatebetweenvariousseniorstakeholdersinthebanks(e.g.headofdepartments,\nbusinessprocessowners)aswellasPwCteamsinAsiaPac,USandUKandcrossfunction\nteams.\n PreparationoftheAuditLongFormReport(“ALFR”)whichissubmittedtotheMonetary\nAuthorityofSingaporeforSingaporeregisteredbanksandbranches.TheALFRincludes\ncontroldeficienciesobservedinthebankandrecommendationsforenhancementsinline\nwithindustrypracticeandregulatorsexpectations.\n KeyclientsincludeCommerzbankAG(SingaporeBranch),MacquarieCapitalSecurities,\nMaybankKimEngHoldingsGroup,HongLeongBank(SingaporeBranch),DBSVickers\nSingapore,BNPParibasSecuritiesSingaporeandSchroder&Co.(Asia).\nAwards\n SingaporeScholar,SingaporeMinistryofForeignAffairs(2006)\n Awarded thePwC Experience Award byPwC HKand China–Recognise 2016 fordedication\ntocollaborationandsharing.\n",
    "skills": [
      "communication"
    ],
    "experience": 0,
    "education": [
      "Countering Financing of Terrorism (AML/CFT) and regulations for banks and capital",
      " Developed strong project management and communication skills through the planning and",
      "Education",
      " BachelorsofAccounting(Hons)fromNanyangTechnologicalUniversity(Singapore)",
      "accounts within 6 weeks and required coordination and communication with various",
      "recommendations based on our experience/understanding of the local regulator’s",
      " Reviewofcapitaladequacycalculationsanddisclosurestoensureitscompliancewiththe",
      "capitaladequacyframeworkasmandatedbytheReserveBankofNewZealand.",
      " KeyclientsincludeCommerzbankAG(SingaporeBranch),MacquarieCapitalSecurities,",
      " Awarded thePwC Experience Award byPwC HKand China–Recognise 2016 fordedication"
    ],
    "personal_info": {
      "email": "oliviapeter@hotmail.com",
      "phone": "+6584069099"
    },
    "timestamp": "2025-06-12T11:11:56.908492"
  },
  {
    "file_path": "C:\\Users\\vasis\\Downloads\\resumeData\\PWC_Penny Lim_Risk AM.pdf",
    "name": "Penny Lim",
    "raw_text": "PENNY LIM\nContact No: 9171 6979\nEmail: penny.lim.ay@gmail.com\nWORK EXPERIENCE\nPricewaterhouseCoopers Risk Services Pte. Ltd.\nRisk Assurance Assistant Manager – Governance, Risk and Controls Jul 2014 - Present\n Experience in regulatory compliance by assessing companies against MAS regulatory framework for\nrelated compliance requirements such as KYC, AML monitoring, Fit and Proper, Outsourcing\narrangements for Fund Management Companies\n Provide assurance services and assessment of controls in place to propose possible process\nimprovement points for financial performance and operations of businesses including management\nstructures, information systems and control environment\n Experience in a wide range of projects including Internal Audit Review, Business Process Review,\nSarbanes Oxley 404 and J-SOX Compliance Review, Control Self Assessment Implementation and SSAE\n16 internal control reviews\n Delivering a broad range of innovative and cost-effective solutions for financial control regulatory\nreporting, shareholder value and technology issues\n Specialization: Asset Management, Real Estate, Construction, Manufacturing, Shipping, Retail,\nFinancial Institutes\n Key clients: Effissimo Capital Management, Tokai Tokyo Investment Management Singapore, Tahan\nCapital Management, VisVires Capital Asia Pte Ltd, The Institute Of Banking & Finance, United\nEngineers Limited, Wheelock Properties, Straits Construction Group Pte. Ltd., Hi-P International. Ltd,\nAPL Logistics, Miclyn Express Offshore, Pan-United Corporation, Eu Yan Sang International, Toyota\nMotors Asia Pacific Ltd\nPriceWaterhouseCoopers LLP\nAssurance Senior Associate – External Audit Services Sep 2012 – Jun 2014\n Assisted the clients to ensure that their financials were stated in a true and fair manner for their\nstakeholders and were also in compliance to the required regulatory standards\n Involved in the review of financial performance and control environment to assess the effectiveness of\nthese existing controls, with the aim to propose process improvement points to help the organization\nachieve its objectives\n Performed special audits which includes agreed upon procedures to test specific areas as requested by\nclient\n Specialization: Asset Management, Brokerages, Financial Institutes, Real Estate, Manufacturing and\nRetail\n Key clients: NTUC Income Insurance Co-operative, CLSA (Credit Lyonnais Securities Asia), Skandinaviska\nEnskilda Banken AB, Mapletree Industrial Fund, Singapore Land Limited, Johnson Controls Holding (S)\nPte. Ltd., Brenntag Pte. Ltd., Sumitomo Chemical Singapore Pte Ltd, Asia Pacific Breweries Ltd, The\nBoston Consulting Group, PropertyGuru, Performance Premium, Cold Storage Singapore\nKPMG LLP (Singapore)\nAudit Intern- Financial Services Dec 2011 - Feb 2012\n Worked on 4 major audit projects to analyze the health of these companies' financial statements\n Performed substantial testing on these financial statements and process walk-through to ensure that\nthe accounts are complete and accurate\nKPMG LLP (Singapore)\nIT Advisory Intern- Enterprise Resource Planning Jun 2011 - Aug 2011\n Ensured adequacy and effectiveness of the mitigating controls in client’s IT systems\n Assisted in the implementation of SAP GRC (Governance, Risk and Compliance) Access Control system\n Completed post-implementation reviews and negative testing of client’s system, to ensure proper\nsegregation of control\nSBA Stone Forest Corporate Advisory (Beijing) Co. Ltd\nAccounts and Advisory Intern Apr 2010 - Aug 2010\n Liaised with banks and clients on accounts transactions\n Provided risk assurance to corporations in accordance with Basel II regulations\n Provided advisory services and assisted foreign enterprises to set up Regional Offices (ROs) and Wholly\nForeign Owned Enterprises (WFOEs)\nOTHER QUALIFICATIONS\n Certified Public Accountant (CPA) Singapore Since September 2015\n Currently pursuing Certified Internal Auditor (CIA)\nACADEMIC QUALIFICATIONS\nSingapore Management University (SMU) Aug 2008 - Aug 2012\nCompleted Bachelor in Accountancy, Second Major in Corporate Communication\nRouen Business School (France) Aug 2010 - Dec 2010\nCompleted an exchange semester under the Master Grande Ecole Programme with 3 distinctions\nCO-CURRICULAR ACTIVITIES\nAIESEC Romania – Global Community Development Programme\nVolunteer English Lesson Instructor Jun 2012 - Aug 2012\n Plan, prepare and deliver instructional and classroom activities to facilitate active learning of the\nEnglish language for 30 pre-school students over a period of 6 weeks in Brasov, Romania\nSingapore Chamber of Commerce and Industry (China)- SingCham Shenyang Business Visit\nParticipant representing SMU Jun 2010\n Invitation by Shenyang Municipal Government to study the city's business environment and explore\nopportunities in areas including real estate, retail, professional services, trading, etc.\nBusiness Study Mission to Scandinavia (Sweden, Norway, Denmark)\nParticipant representing SMU Jun 2009\n 13-day trip to established companies such as Lego, Vestas and Novo Nordisk\n Gained essential knowledge of the importance of national branding in Scandinavian firms, business\nopportunities and challenges present through networking events\nSMU Peer Helpers\nSenior Peer Helper Aug 2009 - Aug 2012\n Promote mental well-being among the student community and run events during school term to\nproactively reach out to the school community to educate them on physical and mental wellness\nSMU Banking and Finance Interest Group\nAnalyst Dec 2009 - Aug 2011\n Analyzed portfolios of banks in the private banking and wealth management sector and synthesizing\nthese materials for presentation to fellow analysts\n Participated in Finance and Business Strategic case competitions to obtain essential understanding and\nknowledge of the financial sector\nProject Kinabuhi (The Philippines)\nHead of Education Department Sep 2008 - Dec 2008\n Organized and participated in the 21-day Overseas Community Project to The Philippines\n Led the Education Department to plan and schedule Mathematics, Science, Drama and Creativity and\nIT knowledge classes to 500 Grade 5 and 6 students\nCommunity Involvement Programme\nTeam Representative Jan 2007 - Dec 2007\n Started CIP programme for fellow students at the Singapore Zoological Gardens and the Jurong\nBirdpark, organized and liaised with representatives from various organizations to ensure smooth\nrunning of programmes\nAWARDS/ACHIEVEMENTS\n PwC Risk Assurance Star Awards Winner Dec 2015\n PwC Experience Award Winner 2013, 2014, 2015\n Top 3 teams at the Credit Suisse Business Case Competition Nov 2011\nSKILLS/LANGUAGES\n Excellent in spoken and written English and Business Mandarin\n Proficiency in Microsoft Office, Excel\nOTHERS\n Valyrian Thinking Business Consulting Workshop by Dragonfly LLC Alumnus\n Mental Health First Aid (Singapore) Course by Changi General Hospital, SingHealth\n First Aid Course, Singapore Red Cross Society\n Kayaking Proficiency 1 Star Personal Skill Award, Council of the Singapore Canoe Federation\n",
    "skills": [
      "communication",
      "excel",
      "finance"
    ],
    "experience": 0,
    "education": [
      " Key clients: Effissimo Capital Management, Tokai Tokyo Investment Management Singapore, Tahan",
      "Capital Management, VisVires Capital Asia Pte Ltd, The Institute Of Banking & Finance, United",
      "Pte. Ltd., Brenntag Pte. Ltd., Sumitomo Chemical Singapore Pte Ltd, Asia Pacific Breweries Ltd, The",
      "OTHER QUALIFICATIONS",
      "ACADEMIC QUALIFICATIONS",
      "Completed Bachelor in Accountancy, Second Major in Corporate Communication",
      "Completed an exchange semester under the Master Grande Ecole Programme with 3 distinctions",
      "Business Study Mission to Scandinavia (Sweden, Norway, Denmark)",
      " Gained essential knowledge of the importance of national branding in Scandinavian firms, business",
      "proactively reach out to the school community to educate them on physical and mental wellness",
      " Participated in Finance and Business Strategic case competitions to obtain essential understanding and",
      "Head of Education Department Sep 2008 - Dec 2008",
      " Led the Education Department to plan and schedule Mathematics, Science, Drama and Creativity and",
      " Started CIP programme for fellow students at the Singapore Zoological Gardens and the Jurong",
      " Top 3 teams at the Credit Suisse Business Case Competition Nov 2011",
      " Kayaking Proficiency 1 Star Personal Skill Award, Council of the Singapore Canoe Federation"
    ],
    "personal_info": {
      "email": "penny.lim.ay@gmail.com",
      "phone": ""
    },
    "timestamp": "2025-06-12T11:11:57.126878"
  },
  {
    "file_path": "C:\\Users\\vasis\\Downloads\\resumeData\\PWC_Wong Zhong Ming_Senior Audit Associate.pdf",
    "name": "Personal Details",
    "raw_text": "Curriculum Vitae\nPersonal Details\nName: Wong Zhong Ming NRIC No: S8929509B\nAddress: Blk 8A Boon Tiong Road,\n#10-75 Singapore 164008\nDate of Birth: 26 August 1989 Race: Chinese\nNationality: Singaporean Marital Status: Single\nMobile No: 81339882 Email: zhongming.wong@gmail.com\nAvailability: 1 month notice\nWorking Experiences\n1. PricewaterHouse Coopers LLP (Singapore)\nJob Appointment : Senior Audit Associate (Grade 2) – Regulatory Advisory (Financial Services)\nPeriod : Dec’15 – Current\nJob Responsibilities : Enclosed below,\n Review the risk profiling assessment of customers according to their respective risk categories and the\napplication of the appropriate due diligence procedures. Performance of KYC remediation of a global\nbank to ensure compliance with MAS regulations, including assessment of account risk rating.\n Review the adequacy of KYC/AML assessments performed for suspicious transaction reporting filed for\nvarious private banks, and the adequacy of the enhanced monitoring controls in place. Responsible for\nreview of KYC/AML performed for the purposes of periodic review, including review of the adequacy\nand robustness of assessments performed for high risk clients when determining AML risk rating.\n Perform audit support on KYC/AML for various financial institutions, including review of customer on\nboarding documentation to ascertain completeness of KYC/AML documentation and consistency of\nAML risk profiling.\n Assisted to review, develop and recommend implementation of internal all-rounded Compliance\nMonitoring Framework and developing compliance frameworks, policies and procedures\n Acting as the main point-of-contact for Asset Management Clients for any regulatory/compliance\nmatters and includes keeping the company abreast of any regulatory updates and changes from time to\ntime\n Assisted to prepare and provide compliance training and build-up the compliance culture within newly\nlicensed Asset Management clients\n Perform gap analysis of Policies and Procedures for Fund Management companies pertaining to the\nvarious applicable regulatory compliance updates in accordance with the Securities & Futures Act\n(SFA), MAS Guidelines and/or Notices and industry best practices.\n Ability to work closely with the stakeholders and other support departments to perform work under tight\ndeadline.\n Regulatory Advisory experience in Private Banks, Private Equity and Asset Managers (RFMC and\nCMSL Holders)\n Knowledge in MAS 626, Private Banking Control, Securities and Futures Act (SFA), Financial Advisers\nAct (FAA) and Risk-Based Capital Requirements for Fund Management Companies\n2. Ernst & Young LLP (Singapore)\nJob Appointment : Senior Audit Associate (Grade1) – Financial Services Office (FSO)\nPeriod : Sep’13 – Dec’15\nJob Responsibilities : Enclosed below,\n Involved in Financial Reporting, Compliance Audit Review, Risk Management, conducting AML/KYC\nand Due Diligence reviews to ensure compliance with the relevant standards (US GAAP/IFRS/MAS\nrequirements)\n Assist in the preparation and execution of both Financial and Compliance audits and reviews of business\nprocesses, integrity of financial information and internal control systems\n Responsible for identifying opportunities to improve the reliability of processes and use of financial\nresources\n Coordinating with clients to gather information and identify gaps in controls and make practical\nrecommendations\n Acting as the main point-of-contact for Asset Management Clients for any regulatory/compliance\nmatters and includes keeping the company abreast of any regulatory updates and changes from time to\ntime\n Audit experience in Merchant Banks, Private Equity, REITs, Trustee Co and Asset Management\nCompanies\n Appointed to be MAS Inspector in various MAS Agreed-Upon Procedures (AUP) for MAS Regulatory\nCompliance\n3. PSA Corporation Ltd\nJob Appointment : Accounts Executive\nPeriod : Sep’12 – Sep’13\nJob Responsibilities : Enclosed below,\n Management Reporting (Full Set)\n Prepares periodic financial reports\n GST Submission and Reporting\n Tax Computation\n Reconciliation of provision and various accounts\n Raising of Journal Vouchers\n4. Nippon Yusen Kaisha(NYK) Shipmangement Pte Ltd\nJob Appointment : Accounts Assistant\nPeriod : Jul ’11 – Sep’12\nJob Responsibilities : Enclosed below,\n Accounts Payable Functions\n Vessel Accounts Management\n Checking and verification of portage bills (monthly Ship expenses), manning agent statement of account\nand raising of journals.\n Prepare journals for accrual of crew wages / manning expenses, journal for Lub Oil ROB, journal for\ninsurance prepayments, etc.\n Preparation of TT remittances for crew home allotment.\n Reconciliation of Maritime balance sheet items e.g. home allotment, chat card inventory, ROB\nprovision, advance to port agent, etc.\n Compilation and preparation of monthly accounting reports, quarterly closing reports and provisional\nreports.\nAcademic Qualifications\n2012-Current CPA (Australia)\nCPA (Aust.) Holder\n2010-2012 Royal Melbourne Institute of Technology\nBachelor in Business (Accountancy)\n2006-2009 Ngee Ann Polytechnic\nDiploma in Accountancy\n2002-2005 Henderson Secondary School\nGCE ‘O’ Levels\n1996-2001 River Valley Primary School\nPSLE\nCo-Curriculum Achievements\nNPCC (2002 -2005) -National Youth Achievement Award (Bronze)\n-CCA Merit Award (NPCC)\nNgee Ann Poly (2006 – 2009) -Freshmen Orientation Sub-Committee Member\n-Freshmen Recruitment Sub-Committee Member\n-Ngee Ann Canoeing Club Member\nNippon Yusen Kaisha (2011- 2012) - Social Recreational Committee Member\nPersonal Skills\nSoftware Skills\n1. Microsoft Office (Excel, Pivot, V-lookup, Powerpoint) Excellent\n2. Bloomberg Intermediate\n3. Thomson Reuters Intermediate\n4. Macromedia Flash and Dreamweaver. Intermediate\n5. MYOB Intermediate\n6. ACCPAC Intermediate\n7. Oracle Financial Systems Intermediate\n8. Hyperion Financial Mgmt Systems Intermediate\nLanguage Skills\n1. English : Conversant and writes well\n2. Chinese : Conversant and writes well\n3. Cantonese : Conversant\nPersonal Strengths\n1. Independent and adaptive\n2. Pleasant disposition\n3. Highly motivated personality\n4. Excellent Interpersonal skills\n5. Good interpersonal skills and attitude to work with due diligence\n6. Strong Analytical and communication skills\nNational Service Details\nRank: Corporal\nDate of Enlistment: 13 July 2009 Performance: Very Good\nOperational Ready Date: 12 May 2011 Conduct: Outstanding\nAchievement: WY 10/11 SAF Outstanding Suggestor Award (Bronze)\nReferences\nName: (LTC) Koh Ban Chuan, Richard\nCompany: Singapore Armed Forces\nPosition: Wing Commander, Echo Wing, Officer Cadet School(OCS)\nContact: +65 91870473\nName: (Ms) Lynn Teo\nCompany: Nippon Yusen Kaisha(NYK) Shipmanagement Pte Ltd\nPosition: Deputy Manager (Accounts)\nContact: +65 9297 2824\n",
    "skills": [
      "accounting",
      "communication",
      "excel"
    ],
    "experience": 0,
    "education": [
      " Review the risk profiling assessment of customers according to their respective risk categories and the",
      "application of the appropriate due diligence procedures. Performance of KYC remediation of a global",
      "various applicable regulatory compliance updates in accordance with the Securities & Futures Act",
      "Act (FAA) and Risk-Based Capital Requirements for Fund Management Companies",
      " Coordinating with clients to gather information and identify gaps in controls and make practical",
      " Checking and verification of portage bills (monthly Ship expenses), manning agent statement of account",
      " Reconciliation of Maritime balance sheet items e.g. home allotment, chat card inventory, ROB",
      "Academic Qualifications",
      "Bachelor in Business (Accountancy)",
      "-CCA Merit Award (NPCC)",
      "-Ngee Ann Canoeing Club Member",
      "3. Cantonese : Conversant",
      "6. Strong Analytical and communication skills",
      "Position: Wing Commander, Echo Wing, Officer Cadet School(OCS)"
    ],
    "personal_info": {
      "email": "zhongming.wong@gmail.com",
      "phone": "2002 -2005"
    },
    "timestamp": "2025-06-12T11:11:57.338572"
  },
  {
    "file_path": "C:\\Users\\vasis\\Downloads\\resumeData\\Reliance AM_TasneemNasrulla_Compliance Officer.pdf",
    "name": "Tasneem Nasrulla",
    "raw_text": "TASNEEM NASRULLA\nPROFESSIONAL EXPERIENCE\nApr 2016 – Compliance Officer - Reliance Asset Management (S) Pte Ltd, Singapore\nPresent Responsible for the Regulatory and Investment Compliance of a Capital Market Services licensed Fund Manager.\n- Mandating and ensuring Regulatory Reporting & Compliance. Liaising with regulators and authorities on all\ncompliance/regulatory matters in different jurisdictions.\n- Preparing monthly Compliance Report to the Board of Directors & Risk Report to CRO of Parent Company.\n- Keeping the company abreast of regulatory developments with the Monetary Authority of Singapore(MAS),\nU.S. Securities and Exchange Commission, Financial Industry Regulatory Authority (FINRA) & Securities and\nExchange Board of India (SEBI). Periodic SEC,, SEBI, GABRIEL (FCA) and FATCA reporting\n- Managing ongoing AML/CFT monitoring\n- Reviewing of all Customer Due Diligence/ KYC documentations, onboarding and ongoing monitoring of clients\n& contract agreements\n- Facilitating semi-annual internal and external audits, addressing concerns highlighted & ensuring follow up\nwith Audit Committee and Board of Directors\n- Reviewing, enhancing and implementing new policies and processes to enhance compliance & ensure proper\ninternal control, segregation of functions, mitigation of conflicts of interest\n- Identifying & reporting risks to the Risk Management Committee. Implementing risk approved mitigation\nmeasures and updating the risk bank.\n- Preparing board resolutions & coordinating with Company Secretary with respect to periodic filings like MAS\n& ACRA\n- Reviewing ongoing marketing materials and newsletters\n- Successfully wrapped up MAS Audit upon joining the Company.\n- Updated and implemented all company manuals (i.e Compliance, AML, Risk Management, Investment, IT\nPolicy & Procedures, Employee Handbook) as well as CDD Onboarding & Review Forms.\n- Liaising with distributors of various Funds from reviewing distribution agreements to onboarding and review\nof all distributors and platforms.\n- Overseeing all Audit Committee, Risk Management Committee & Board of Directors Meetings including\ndrafting of all minutes of the meetings.\nDec 2013 – Compliance Manager (Reinsurance) – RKH Specialty Asia Pacific Pte Ltd, Singapore\nMar 2016 Responsible for overseeing the Corporate Compliance Program for the company\n- Working in association with Group Compliance in London to ensure policies and procedures are implemented\neffectively within RKH. Adhering to FCA regulations in like with parent company in UK. Taking ownership of\ncertain aspects of the firm’s policies and procedures that address RKH’s regulatory risks, including drafting and\nimplementing new policies and procedures.\n- Acting as the liaison officer with the MAS and to support the CEO in the submission of all MAS returns,\napplications and notifications.\n- Supporting the anti-money laundering / sanctions/ financial crime function as stipulated by Singapore\nregulations and in line with RKH’s policies and procedures. Working closely with the Operations and\nCompliance Representatives (OCRs) from the respective business lines with regards to approval process for\nSecurity, Third Parties Producers\n- Conduct monthly internal audit / file reviews on all RKH placements in Singapore & London.\n- Providing assistance to the business on compliance/ regulatory matters and client due diligence (CDD) process.\n- Responsible for continuous compliance training of RKH Singapore Staff\n- Providing compliance advice and assistance to Howden Korea (Retail Insurance) with respect to CDD and\nsanctions.\nAug 2013 - Compliance Manager – Global Financial Consultants Pte Ltd, Singapore\nOct 2013 Responsible for overseeing the Corporate Compliance Program for the company.\n- Represented the firm in communication and interaction with the Monetary Authority of Singapore (MAS)\n- Maintained all regulatory requirements for the Exempt Financial Advisory (EFA) license awarded by MAS\n- Created the new organization structure for the company in adherence with the Corporate Governance\nGuidelines by Monetary Authority of Singapore (MAS)\nJan 2012 – VP – Compliance, LVP Premier Asset Management Pte Ltd, Singapore\nFeb 2013 Responsible for overseeing the Corporate Compliance Program for the company.\n- Represented the firm in communication and interaction with the Monetary Authority of Singapore (MAS) &\nexternal auditors.\n- Maintained all regulatory requirements for the Exempt Fund Manager (EFM) & Exempt Financial Advisory\n(EFA) licenses awarded by MAS, this includes designing the compliance manual for the business.\n- Aligned processes & procedures to ensure compliance, for the transition to the Registered FMC Regime.\n- Successfully set up an in-house open-ended fund from reviewing the Private Placement Memorandum (PPM)\nto creating processes for valuations, trading and receipt of client monies.\nMay 2010 – Compliance Manager, Calypso Capital Pte Ltd, Singapore\nDec 2011 Responsible for overseeing not only the regulatory compliance but also the overall operation of the business.\n- Played an integral role in setting up the company, with specific responsibility for licensing (Exempt Fund\nManager & Exempt Financial Advisory)\n- Successfully completed the MAS Audit with KPMG, the MAS appointed external auditor.\n- Designed & codified key policies – account opening & KYC documentation, compliance, HR & accounting\n- Successfully managed the operational administration of the company\nSept 2009 – Associate Vice President, IIFL Private Wealth, Singapore\nApr 2010 Responsible for Business Development with Wealth Management Institutions & Clients in South East Asia.\n- Developed ties with various product team heads – Key emphasis being empanelment of IIFL’s Fund.\n- Successfully handled firm & product marketing with relationship managers & product teams at leading private\nbanks in Switzerland & Dubai.\nJune 2007 – Relationship Manager (Consumer Banking), Standard Chartered Bank, Singapore\nJune 2009 Responsible for providing financial advice, maintenance & growth of existing customer base.\n- Structured product portfolios for new & existing clients (250 clients, SGD 70 million AUM), based on needs\nassessment\n- Successfully managed client relationships, resulting in increased AUM for existing clients & acquisition of new\nclients. Consistently achieved or exceeded personal sales target of SGD 180K per quarter.\nNov 2005 – Associate Banker, Citibank Non-Resident Indian (NRI) Business, Singapore\nJune 2007 Responsible for management of on-going client servicing & supporting RM’s heading up the Indonesian Segment.\n- Successfully handled the flow of information between middle & back offices, and clients, management &\nrelationship managers, to enable timely decision making and risk management\n- End-to-end interface for clients in the trades of investment products i.e. mutual funds, bonds and structured\nnotes. In-charge of the order placement for Indonesian Team and maintained log of Investments/Revenues.\nEDUCATION\nCertified Anti-Money Laundering Specialist - CAMS Examination in March 2017\nOnline FATCA Course - Association of Certified Financial Crime Specialists (ACFCS) Currently Studying\nCertificate in Reinsurance - Singapore College of Insurance May 2014\nFICS Accredited - Specialist Diploma in Compliance June 2013\nInternational Compliance & Training Academy Pte Ltd, Singapore\nModule 1 – Merit Pass; Module 2 – Distinction Pass; Module 3 – Distinction Pass; Module 5 – Distinction Pass\nCertificate in Fund Administration - Nanyang Polytechnic, Singapore Apr 2013\nUnderstanding The Financial Advisers Act (Cap 110) - Singapore College of Insurance Mar 2013\nInternational Certificate in AML Awareness - International Compliance Association, Singapore Jan 2013\nCapital Markets & Financial Advisory Services (CFMAS) Modules – 9A July 2012\nModule 1; 5; 9; HI July 2007\nBachelor of Science in Banking & Finance - University of London (External Programme), Singapore 2000 - 2006\nGraduated with Honors; Scored in Principles of Banking, Corporate Finance & Banking Operations & Risk Analysis\nDiploma in Accounting & Finance - Temasek Polytechnic, Singapore 1997 - 2000\nCOMPETENCIES & SKILLS\n● Communication skills – particularly detailed report writing & the ability to assimilate and present complex information simple\nand accurately. Relationship Building with key stakeholders.\n● Stakeholder relationship management and inter-personal skills\n● Technical problem solving abilities\n● Accuracy and attention to detail\n● Negotiation skills\n",
    "skills": [
      "accounting",
      "communication",
      "finance"
    ],
    "experience": 0,
    "education": [
      "Present Responsible for the Regulatory and Investment Compliance of a Capital Market Services licensed Fund Manager.",
      "Exchange Board of India (SEBI). Periodic SEC,, SEBI, GABRIEL (FCA) and FATCA reporting",
      "effectively within RKH. Adhering to FCA regulations in like with parent company in UK. Taking ownership of",
      "applications and notifications.",
      "- Represented the firm in communication and interaction with the Monetary Authority of Singapore (MAS)",
      "- Represented the firm in communication and interaction with the Monetary Authority of Singapore (MAS) &",
      "May 2010 – Compliance Manager, Calypso Capital Pte Ltd, Singapore",
      "EDUCATION",
      "Certified Anti-Money Laundering Specialist - CAMS Examination in March 2017",
      "Online FATCA Course - Association of Certified Financial Crime Specialists (ACFCS) Currently Studying",
      "Certificate in Reinsurance - Singapore College of Insurance May 2014",
      "International Compliance & Training Academy Pte Ltd, Singapore",
      "Certificate in Fund Administration - Nanyang Polytechnic, Singapore Apr 2013",
      "Understanding The Financial Advisers Act (Cap 110) - Singapore College of Insurance Mar 2013",
      "International Certificate in AML Awareness - International Compliance Association, Singapore Jan 2013",
      "Capital Markets & Financial Advisory Services (CFMAS) Modules – 9A July 2012",
      "Bachelor of Science in Banking & Finance - University of London (External Programme), Singapore 2000 - 2006",
      "● Communication skills – particularly detailed report writing & the ability to assimilate and present complex information simple",
      "● Technical problem solving abilities"
    ],
    "personal_info": {
      "email": "",
      "phone": "2000 - 2006"
    },
    "timestamp": "2025-06-12T11:11:57.583934"
  },
  {
    "file_path": "C:\\Users\\vasis\\Downloads\\resumeData\\Resume --Rohini Prakash.pdf",
    "name": "Rohini Prakash, Ca",
    "raw_text": "ROHINI PRAKASH, CA\nSINGAPORE |+ 65 98624747 |rohiniprakash1@gmail.com\nINVESTOR RELATIONS, FUND STRUCTURING, CONTROLLERSHIP &\nCOMPLIANCE\nHighly result driven detail oriented professional with experience in Fund management, structuring, investor\nrelations, regulatory compliance, fund raising, deal structuring, valuations & controllership.\nKEY SKILLS\nFund Controller Financial Analysis Fund Management\nAccounting/ reporting/audits Fund performance metrics Fund tax structuring\nCross border taxation Valuations review Fund legal documentation\nCompliance/ internal Controls Fund management/ treasury Investor meetings\nFund management/ treasury Budgeting & cost control Due diligence\nStructures –LP/LLC\nEXPERIENCE\nXANDER GROUP, SINGAPORE Nov 2010 till date\nEmerging market focussed Institutional investment firm backed by the Rothschild Investment Trust and Getty\nFamily, with $2BN AUM primarily invested in real estate, infrastructure, hospitality and retail sectors.\nVICE PRESIDENT\nStructured funds & real estate investments, assisted in Fund raising, managed Fund’s investor reporting,\nregulatory compliance, valuation, performance assessment, treasury, accounting and taxation.\n Structured cross border Funds, worked with consultants on preparation and review of Fund structures and\ndocumentation/ setting up of entities/ obtaining tax exemptions (13X/13R).\n Structure/ manage investment into underlying investee companies (equity/ debt). Review valuations/\nassess performance (member of the Valuation Committee across Funds).\n Built and managing a team of five personnel for running the operations of 7 Funds with a corpus of `USD 2\nbillion (including accounting, taxation, investor communication/ queries, treasury, compliance,\ninvestments/ divestments etc.). Developed processes and internal controls for financial reporting.\n Assisted in preparation of pitches/ due diligence documents/ track record for fund raising. Attended\ndiscussions/ meetings with prospective investors.\n Screened, identified and transitioned work to third party vendor for automating accounting and reporting\nprocess. Currently implementing an investor portal completely integrated with the accounting system\n Initial one year period worked in Asset management – responsible for reviewing performance/ making\nimprovements/ tracking of underlying real estate investments\nCOPAL AMBA, DELHI Jan 2010 – Oct2010\nCopal Amba is a leading financial research and analytics company owned by Moody’s. It’s clients include\nleading bulge bracket financial institutions, Fortune 100 corporations, investment banks and asset managers.\nHEAD RISK & COMPLIANCE\nSet up and managed the risk framework, lead customer audits, assisted in new customer proposals to leading\nbanks.\n Reviewed, developed, and strengthened the risk framework of the Company across several locations.\nrohiniprakash1@gmail.com| +6598624747| PAGE 1\n Set up risk framework, documented policies and trained staff at new office premises in Beijing to ensure\ncompliance with service level agreements. Successful in obtaining client approval for commencing\noperations at the site.\n Successfully prepared for and front-ended several client audits of leading banks/ corporations.\n Worked on relationship building with existing/ potential customers. Attended relationship building\nmeeting with the largest client along with co-founder of Copal.\n Assisted in preparing pitches and also presented the compliance framework to prospective clients. Built\nand managed the four member Compliance team. Responsible for appraisals/ development of team.\n Conducted operational reviews to identify cost inefficiencies. Successful in reducing/controlling several\noperating costs.\n Built and managed the four member Compliance team. Responsible for appraisals/ development of team.\nKPMG, DELHI & LONDON Jul 2002 – Oct2009\nASSISTANT MANAGER, ASSURANCE & ADVISORY DIVISION\n Effectively managed financial statement / internal control/ SOX audits for several large and mid-sized\ncorporations (BBC, Panasonic, Actis, Apax, Dentsu, Canon, Timex, Jubilant, Group 4, CSC, Cadence,\nAllied, Diageo)\n Managed/ supervised simultaneous projects including formulation of budget, assigning staff, monitoring\nprogress, managing the teams, presenting and resolving significant issues, debrief meeting with senior\nmanagement and invoicing.\n Seconded to the London Private Equity Assurance division. Conducted the audit of several Private Equity\nFirms (Apax, Morgan Grenfell).\n Successfully completed a complex (merger/ demerger) multi-location accounting advisory assignment for\nGE with an extremely demanding deadline.\n Instrumental in identifying gaps and inefficiencies in the finance function of HCL which helped reduce\nreporting timelines significantly. Presented the process maps indicating gaps and suggested measures to\nthe CFO and Vice-Presidents heading the various Finance divisions.\n Seconded to the Department of Professional Practice and worked on queries received from teams across\nKPMG locations in India on application of accounting standards and corporate laws.\n Conducted trainings on the KPMG audit methodology/ accounting standards for Executives and Staff\nAccountants.\nEDUCATION & QUALIFICATIONS\nInstitute of Chartered Accountants of India New Delhi, India\nAssociate Member – Cleared final examination in 1st attempt Nov 2006\nSriram College of Commerce, University of Delhi New Delhi, India\nBachelors of Commerce (Honors) - First Division May 2002\nD.P.S. R.K. Puram New Delhi, India\nCommerce –scored 90% March 1999\nOTHER SKILLS & INTERESTS\nReading\nTravel\nGardening\nrohiniprakash1@gmail.com| +6598624747| PAGE 2\n",
    "skills": [
      "accounting",
      "ca",
      "communication",
      "finance"
    ],
    "experience": 0,
    "education": [
      "ROHINI PRAKASH, CA",
      "billion (including accounting, taxation, investor communication/ queries, treasury, compliance,",
      "COPAL AMBA, DELHI Jan 2010 – Oct2010",
      "Copal Amba is a leading financial research and analytics company owned by Moody’s. It’s clients include",
      " Reviewed, developed, and strengthened the risk framework of the Company across several locations.",
      "corporations (BBC, Panasonic, Actis, Apax, Dentsu, Canon, Timex, Jubilant, Group 4, CSC, Cadence,",
      "progress, managing the teams, presenting and resolving significant issues, debrief meeting with senior",
      " Successfully completed a complex (merger/ demerger) multi-location accounting advisory assignment for",
      "reporting timelines significantly. Presented the process maps indicating gaps and suggested measures to",
      "KPMG locations in India on application of accounting standards and corporate laws.",
      "EDUCATION & QUALIFICATIONS",
      "Bachelors of Commerce (Honors) - First Division May 2002"
    ],
    "personal_info": {
      "email": "rohiniprakash1@gmail.com",
      "phone": "65 98624747"
    },
    "timestamp": "2025-06-12T11:11:57.747377"
  },
  {
    "file_path": "C:\\Users\\vasis\\Downloads\\resumeData\\UOB AM_Felyna Lee_Product AVP.pdf",
    "name": "Felyna Lee Hui Chay, Cfa Felyna.Lee@Gmail.Com | (65) 9650 7466",
    "raw_text": "Felyna Lee Hui Chay, CFA felyna.lee@gmail.com | (65) 9650 7466\nRNF Rep. No.: LHC300105930 Singapore citizen | DOB 12 Nov 1987\nEDUCATION\nJun 2012 – Jun 2014 Chartered Financial Analyst (CFA) Programme\n Successfully sat for and passed all three levels of CFA exams on the first attempt\nAug 2006 – May 2010 National University of Singapore (NUS)\n Bachelor of Business Administration (Accountancy) (Honours)\n Presented the NUS BBA (Merit) Scholarship\n Enrolled in the prestigious University Scholars Programme, a multi-disciplinary academic\nprogramme which accepts only 3% of each undergraduate cohort\n Awarded the Dean’s List twice (2006 and 2009) for being in top 5% of Business cohort\n Cumulative Average Point (CAP): 4.32/5.0 (2nd Upper Class Honours)\nJan 2009 – May 2009 University of Edinburgh, Scotland (Student Exchange Programme)\nJan 2004 – Dec 2005 Hwa Chong Institution\n GCE ‘A’ Levels with distinctions in Biology and Economics\nCORPORATE EXPERIENCE\nMar 2014 – Present UOB Asset Management Ltd (UOBAM)\nProduct Development & Marketing Communications, Assistant Vice President\n Selected to be in key strategic initiative working group to cross-sell UOBAM investment\nsolutions to other business segments of UOB Group; driving development of product\ncatalogue\n Selected to be in UOBAM strategic review working group to ensure efficient resource\nallocation to support core/non-core capabilities, developed proposals and designed slides for\nSenior Management\n- Selected to be member of workstream on implementing new capabilities. Developed\nproposal which resulted in resources being dedicated to launch new investment\ncapability.\n Examine regional product suite and develop new product ideas to plug product gaps by\nconducting independent research and determining feasibility with input from Fund Managers\n(FMs), regional Sales and Product teams, and third party strategic partners\n Independently drive process flow to launch new products: Presenting business case and\nobtaining approval from Regional Product Committee, liaising with internal and external\nparties to execute full product launch process (e.g. offering documents, account opening)\n- Currently driving process flow to launch liquid alternative fund\n- Successfully launched global equity fund with smart beta elements\n Provide market intelligence: Analyse data on fund performance and flows compared with\npeers, design slides and present findings at monthly management meetings; designed slides\nfor UOBAM Board of Directors February 2016 meeting\n Engage UOB product team, organise monthly meetings, provide product support\n Analyse features of existing products, develop proposals for improvement while staying\ncompetitive, present case to Senior Management and obtain approval, plan and execute fund\nvariation projects\n- Currently planning and executing fee rationalisation for full suite of existing funds\n- Successfully drove process flow to increase management fees for two funds\n Organised signing event of Memorandum of Understanding in May 2015 between UOBAM\nand Wellington Management Singapore, selected to emcee at signing ceremony guested by\nSenior Management from UOB and Wellington\n Revamped Quarterly Investment Strategy publication by engaging internal and external\nstakeholders; made the content more concise (50% decrease in length) to improve reader\nfriendliness\n Produced marketing materials: Prepared content and designed two thematic publications on\nAsian fixed income and Multi-asset Income investing to support the sales of two focus funds;\nconducted research, drafted content and designed fund brochure and placemat; performed\neditorial checks and layout of monthly fund/market commentaries and Quarterly Investment\nStrategy publication\nPage 1 of 3\nFelyna Lee Hui Chay, CFA felyna.lee@gmail.com | (65) 9650 7466\nRNF Rep. No.: LHC300105930 Singapore citizen | DOB 12 Nov 1987\nREGIONAL EXPERIENCE AND PROJECTS\nRegional Product and Sales Committee (RPSC), Secretariat (January 2016 – Present)\n Developed guidelines and designed slide templates to promote the discussion of new ideas\nand to determine the feasibility of regional launches; obtained buy-in from Product and Sales\nteams from Singapore and five overseas subsidiaries\n Facilitate monthly meetings, consolidate materials and ensure they are in order\nUOB Asset Management Co., Ltd. (Thailand) (August 2015 – October 2015)\nProduct and Investment Strategy (Work Attachment)\n Initiated and obtained approval for 2-month overseas work attachment to gain regional\nexposure with Product & Investment Strategy team which plans and executes the firm’s\nproduct pipeline considering investment market developments and client needs\n Independently completed Due Diligence Questionnaires accurately for submission to UOB\nThailand and UOB Singapore Product Sales Committees\n Performed post launch reviews of unit trusts to analyse performance and AUM raised\n Designed slides for upcoming fund launches and refined fund marketing collateral\nRegional Product Committee (RPC), Secretariat (April 2013 – December 2015)\n Developed Terms of Reference and Guidelines, designed all product approval and reporting\ntemplates to facilitate committee’s oversight of the UOBAM Group’s product-related matters.\nObtained buy-in from regional product teams and committee and rolled out framework within\ntight timeline of two months.\n Facilitated monthly meetings and took minutes, consolidated materials and ensured that they\nare in order\nUOBAM Special Regional Projects (January 2014 – August 2015)\n Foreign Account Tax Compliance Act (FATCA) Working Group, Coordinator\n- Appointed main coordinator to roll out FATCA programme for UOBAM Group (including\n5 overseas subsidiaries) while successfully managing existing Product Development\njobscope in Singapore\n- Set up FATCA project structure for UOBAM Group and coordinated with UOB FATCA\nProject Management Office and multiple UOBAM departments including overseas\nsubsidiaries to ensure that the UOBAM Group implements policies and procedures to\ncomply with regulatory timelines while staying pro-business, incorporated FATCA\nlanguage into all legal documents\n- Presented project status updates at quarterly UOB Project Steering Committee meeting\ncomprising UOB Group’s Senior Management, and monthly UOBAM Regional Risk\nCommittee meetings, including independently conducting major exercise to analyse the\nbusiness impact of FATCA by performing AUM impact analysis\nUOBAM\nApr 2012 – Feb 2014 Product Development & Marketing Communications, Manager\n Designed presentation slides to propose 3-5 year strategic product plan to Senior\nManagement, reviewed products and performed gap analysis, recommended action plans\n Analysed management fees of existing products, created management fee analysis model in\nExcel, demonstrated that increasing management fees for one fund can increase the firm’s\nprofitability while the fund stays competitive, and successfully executed project\n Independently drove process flow to launch funds\n- United Japan Small and Mid Cap Fund: collaborated with Sales and Thai Product team\nto identify launch opportunity, managed added complexity due to appointment of foreign\nsub-manager, designed marketing pitchbook. Liaised with internal and external parties\nto execute full product launch process (documents include Due Diligence Questionnaire,\nOutsourcing Review, Sub-Management Agreement, tripartite Operating Memorandum\nand offering documents)\n- United Asian Local Currency Bond Fund: conducted research and performed peer\ncomparison analysis to support Thai office\n Coordinated termination of United Global Bond Fund; presented business case and obtained\napproval; planned schedule and ensured project timelines were met\n Developed concepts for new products through collaboration with FMs and Sales and\ndesigned product pitchbooks\nPage 2 of 3\nFelyna Lee Hui Chay, CFA felyna.lee@gmail.com | (65) 9650 7466\nRNF Rep. No.: LHC300105930 Singapore citizen | DOB 12 Nov 1987\n In-charge of product development for Taiwan market (Apr 2012 – Apr 2013)\n- Key coordinator for unprecedented project to hold Extraordinary General Meeting (EGM)\nfor unit trust (majority stake held by Taiwanese investors), managed entire process flow\nincluding feasibility study and liaison with legal counsel, obtained successful result to\nchange the fund’s investment objective\n- Analysed information on local business trends and engaged FMs on feasibility of\nproposed ideas, developed model portfolios, ran back-tests, designed pitchbooks\n- Engaged Taiwan Product team with monthly calls on the product pipeline and current\nindustry developments; furnished reports and provided timely support\nUnited Overseas Bank Limited (UOB)\nJan 2012 – Mar 2012 Group Compliance – Asset Management, Senior Officer\n Performed review and testing of investment valuation process flow, identified gaps in\nobtaining prices from external third parties and suggested improvements\n Cleared fund-related marketing materials from a regulatory perspective, eg. monthly fund\ncommentaries, fund marketing collateral (press advertisements, brochures, placemats)\nAug 2010 – Dec 2011 UOB Management Associate (MA) Programme\n 1 out of 27 selected from over 1000 applicants via stringent 5-round selection process for the\nprestigious 16-month UOB MA Programme\n Rotation programme through asset management value chain: regional business sales, unit\ntrust operations and institutional mandate operations and compliance\n- Designed pitchbook for Latin American funds appointing foreign sub-manager\n- Analysed regulatory impact of new Representative Notification Framework on UOBAM,\ndeveloped application templates to facilitate collecting information from employees,\nperformed review and testing of process\n- Cleared marketing materials (eg. fund advertisements and monthly fund commentaries)\n Selected to join special projects team including McKinsey consultants to streamline end-to-\nend process flows for mortgage loans and KYC processes for global financial institutions,\nidentified areas for streamlining, identified fields for system inclusion and liaised with business\nunit on system design\nSKILLS/OTHER INFORMATION\n Successful sat for and passed CMFAS M3, M5, M8A, all on the first attempt\n English – first language, Mandarin – fluent\n Proficient in Microsoft Office; competent in Bloomberg, Morningstar and Lipper\n Interests include piano (ATCL Performance Diploma, Trinity Guildhall, Jun 2008) and singing\n(actively participated in choir from 2000-2014, assumed leadership and teaching positions from\n2002 onwards)\nPage 3 of 3\n",
    "skills": [
      "excel",
      "leadership"
    ],
    "experience": 5,
    "education": [
      "EDUCATION",
      " Bachelor of Business Administration (Accountancy) (Honours)",
      " Enrolled in the prestigious University Scholars Programme, a multi-disciplinary academic",
      " Cumulative Average Point (CAP): 4.32/5.0 (2nd Upper Class Honours)",
      "Product Development & Marketing Communications, Assistant Vice President",
      "catalogue",
      "allocation to support core/non-core capabilities, developed proposals and designed slides for",
      "- Selected to be member of workstream on implementing new capabilities. Developed",
      "proposal which resulted in resources being dedicated to launch new investment",
      "capability.",
      " Independently drive process flow to launch new products: Presenting business case and",
      "competitive, present case to Senior Management and obtain approval, plan and execute fund",
      " Revamped Quarterly Investment Strategy publication by engaging internal and external",
      " Produced marketing materials: Prepared content and designed two thematic publications on",
      "Strategy publication",
      " Foreign Account Tax Compliance Act (FATCA) Working Group, Coordinator",
      "- Appointed main coordinator to roll out FATCA programme for UOBAM Group (including",
      "- Set up FATCA project structure for UOBAM Group and coordinated with UOB FATCA",
      "comply with regulatory timelines while staying pro-business, incorporated FATCA",
      "business impact of FATCA by performing AUM impact analysis",
      "Apr 2012 – Feb 2014 Product Development & Marketing Communications, Manager",
      "Excel, demonstrated that increasing management fees for one fund can increase the firm’s",
      "- United Japan Small and Mid Cap Fund: collaborated with Sales and Thai Product team",
      "- United Asian Local Currency Bond Fund: conducted research and performed peer",
      " Coordinated termination of United Global Bond Fund; presented business case and obtained",
      "- Analysed information on local business trends and engaged FMs on feasibility of",
      "- Engaged Taiwan Product team with monthly calls on the product pipeline and current",
      " 1 out of 27 selected from over 1000 applicants via stringent 5-round selection process for the",
      "- Designed pitchbook for Latin American funds appointing foreign sub-manager",
      "- Analysed regulatory impact of new Representative Notification Framework on UOBAM,",
      "developed application templates to facilitate collecting information from employees,"
    ],
    "personal_info": {
      "email": "felyna.lee@gmail.com",
      "phone": ""
    },
    "timestamp": "2025-06-12T11:11:58.082069"
  },
  {
    "file_path": "C:\\Users\\vasis\\Downloads\\resumeData\\Vertex Venture_Ocvia Freriana_Compliance Lead.pdf",
    "name": "Corruption, Data Research",
    "raw_text": "Ocvia Freriana\nSingapore\nCompliance professional focusing on regulatory compliance, AML, KYC, due diligence, anti-\ncorruption, data research\nExperience\nCompliance Lead at Vertex Venture Management Pte Ltd\nSeptember 2016 - Present (7 months)\nCompliance Manager at Edelweiss Alternative Asset Advisors Pte Limited\nJuly 2014 - September 2016 (2 years 3 months)\n• Create and update compliance policies, such as Compliance Manual, AML/CFT Policy, Screening Policy,\nData Privacy Policy, Anti-Corruption Policy, and Record Retention Policy\n• Ensure compliance with regard to ongoing obligations, required filings, notifications, and declarations as per\nMonetary Authority of Singapore (MAS) requirements\n• In charge of MAS correspondences and regulatory filings\n• Handle AIFMD applications/notifications to EU and UK Regulators for marketing funds to professional\ninvestors in EU countries and UK\n• Handle Switzerland foreign fund marketing requirements for qualified investors by appointing a Swiss\nrepresentative and a Swiss Paying Agent\n• Review fund subscription agreements signed by Investors and KYC documents provided as well as perform\nAML/CFT checks, Accredited/Institutional Investor checks, Professional Investor Checks, US/Non US\nPersons checks, and collect IRS W-9/W-8 forms for FATCA purposes\n• In charge of Enhanced-tier fund (ETF) Scheme applications to MAS for several funds and ongoing\nobligations once approved\n• Ensure compliance of ongoing obligations for Financial Sector Incentive – Fund Management (FSI-FM)\nScheme awarded to the Company by MAS\n• Respond to queries relating to fund marketing compliance for International Operations\n• Provide monthly report on compliance status of Singapore operations to Senior Management of the\nCompany as well as Senior Management of the Parent Company\n• Act as main point of contact for all compliance audit queries from both internal and external auditors\n• Liaise with Company Secretary and Fund Administrators in Singapore and Mauritius\nCompliance Consultant at ComplianceAsia Consulting Pte Ltd\nFebruary 2013 - July 2014 (1 year 6 months)\nWork with companies in the fund management and financial advisory services which are regulated by the\nMonetary Authority of Singapore (MAS)\n• Handle the applications for a Capital Markets Services (CMS) License in Fund Management and Registered\nFund Management Company (RFMC) to MAS\n• Ensure compliance policies and procedures are up to date\n• Provide a compliance monitoring plan taking into account the Company’s internal policies and MAS\nrequirements\n• Advise the Senior Management on compliance matters\n• Handle MAS correspondences and regulatory filings\n• Review the Customer Due Diligence measures and processes in place (including AML/CFT checks)\n• Review the due diligence performed on fund distributors upon appointment and periodically\n• Review marketing materials such as advertisements, presentation decks, factsheets etc. in accordance with\nthe MAS Advertising Guidelines, IMAS Code and other applicable rules and regulations\n• Monitor staff activities with regard to the Company policy on conflict of interest (e.g. personal trading,\nexternal directorships and employments, gifts and entertainment)\nCompliance Analyst, Global Anti-Corruption Team (1 year contract role - renewed annually) at\nAmerican Express\nJuly 2011 - February 2013 (1 year 8 months)\nWork with General Counsel Office, Market Compliance Officers, and Lines of Business to implement an\neffective global anti-corruption program\n• Conduct analysis on entities (i.e. companies/organizations/charities) to determine whether they are State\nOwned Entity (SOE) or Non-SOE\n• Perform research on the company executives to identify Politically Exposed Person (PEP) and screen them\nagainst the sanction lists\n• Review payments made via invoice, Corporate Purchasing Card (CPC), and wire transfer to SOE and Non-\nSOE in all markets\n• Update the list of high risk markets based on Corruption Perceptions Index (CPI) and Office of Foreign\nAssets Control (OFAC) sanctioned countries\n• Perform the Intermediary Certification Process (ICP)\n• Conduct research on the latest news and development on global anti-corruption for quarterly newsletter\ndistributed enterprise-wide\n• Identify and resolve compliance gaps and issues in each market\n• Drive completion for enterprise training, high risk employees training, vendors training, and specific\nprogram training\n• Consolidate quarterly and year-end reporting on the status and progress of the global anti-corruption\nprogram for Senior Management\n• Document policies and guidelines, communications, exceptions, change management as well as\nrepresentation letters made in all markets and lines of business\nContent Quality Analyst at Dow Jones & Company\nJanuary 2009 - July 2011 (2 years 7 months)\n• Support quality testing prior to the launch of the data in Production\no Perform quality checks to determine if responses are appropriate\no Proactively identify data problems and related bugs\no Liaise with Technology and Product departments to resolve data issues\n• Responsible at post-launch to ensure ongoing data quality\no Use internal data quality tools to research and resolve data quality issues\no Conduct research on companies and executives based on company filings, Internet, and other reliable\nsources\no Resolve both internal and external queries escalated by Customer Service Officers in a timely and efficient\nmanner\n• Prepare data quality report that monitors how well the products are meeting and exceeding specified quality\nmetrics and goals\n• Work with Technology Department on internal data mapping, third-party data, and other data in connection\nto Product Development\nMarket Analyst (1 year contract role) at Thomson Reuters\nNovember 2007 - November 2008 (1 year 1 month)\n• Company Fundamental Reports (CFR) Analyst in charge of 8 Markets (Japan, India, China, Taiwan,\nPhilippines, South Korea, Pakistan, and Sri Lanka)\no Ensure that all data flow successfully through several databases and displayed properly on the end products\no Meet the standard Service Level Agreement (SLA) in resolving service queries from both internal and\nexternal customers\no Responsible for data quality, accuracy, timeliness and completeness\no Seek efficiencies in work practices to achieve automation\no Provide feedback on new database/application releases\n• Company Fundamental for Indonesia and Thailand\no Provide customers with financial data of all companies listed on Indonesia Stock Exchange and all Thailand\nlisted companies which file their reports in English\no Keep abreast of daily market activity to ensure that financial information is accurate, timely, and complete\no Build up knowledge of financial regulations and market practices\n• Documentation Library for Indonesia Stock Exchange\no Source financial reports of all companies listed on Indonesia Stock Exchange\no Keep track on upcoming IPOs and ensure that reports will be available in Product by the time the company\nis officially listed on the exchange\no Document policies, procedures, and work processes\nEducation\nNanyang Technological University\nBachelor’s Degree, Banking & Finance and Information Technology, 2004 - 2007\nOcvia Freriana\nSingapore\nCompliance professional focusing on regulatory compliance, AML, KYC, due diligence, anti-\ncorruption, data research\nProfile Notes and Activity (2)\n3/3/2017—View by Ayyaz Ahmad\n3/7/2017—View by Ayyaz Ahmad\n",
    "skills": [
      "finance"
    ],
    "experience": 9,
    "education": [
      "• Ensure compliance with regard to ongoing obligations, required filings, notifications, and declarations as per",
      "• Handle AIFMD applications/notifications to EU and UK Regulators for marketing funds to professional",
      "Persons checks, and collect IRS W-9/W-8 forms for FATCA purposes",
      "• In charge of Enhanced-tier fund (ETF) Scheme applications to MAS for several funds and ongoing",
      "• Handle the applications for a Capital Markets Services (CMS) License in Fund Management and Registered",
      "• Review the due diligence performed on fund distributors upon appointment and periodically",
      "the MAS Advertising Guidelines, IMAS Code and other applicable rules and regulations",
      "American Express",
      "• Perform research on the company executives to identify Politically Exposed Person (PEP) and screen them",
      "• Review payments made via invoice, Corporate Purchasing Card (CPC), and wire transfer to SOE and Non-",
      "• Perform the Intermediary Certification Process (ICP)",
      "• Document policies and guidelines, communications, exceptions, change management as well as",
      "o Resolve both internal and external queries escalated by Customer Service Officers in a timely and efficient",
      "o Provide feedback on new database/application releases",
      "Education",
      "Nanyang Technological University",
      "Bachelor’s Degree, Banking & Finance and Information Technology, 2004 - 2007"
    ],
    "personal_info": {
      "email": "",
      "phone": "2004 - 2007"
    },
    "timestamp": "2025-06-12T11:11:58.197954"
  },
  {
    "file_path": "C:\\Users\\vasis\\Downloads\\resumeData\\Vickers Financial_Ryan Tang_Compliance Officer.pdf",
    "name": "Ryan Tang",
    "raw_text": "Ryan Tang\nCompliance Professional\nEmail: ryantangtg19@gmail.com\nurl: http://sg.linkedin.com/pub/ryan-tang/58/ba5/496\nMobile: (65) 97580537\nPROFILE\n• A Compliance Officer with 3.5 years of experience in a venture capital firm that is regulated by the Monetary\nAuthority of Singapore (“MAS”) under the Capital Market Services (CMS) Licence scheme\n• Strong understanding and knowledge of the Securities and Futures Act and other fund management regulations in\nSingapore\n• Analytical mind with clear, logical thought process\n• Excellent communication and written skills\nEXPERIENCE\nCompliance Officer at Vickers Financial Group (S) Pte Ltd\nJuly 2013 to Present (3 years 7 months)\nCompliance Duties:\n• Establishing and updating of the fund manager's policies and procedures to comply with all the relevant MAS\nregulations\n• Conducting of on-boarding due diligence for investors, ongoing Know Your Customer (KYC) monitoring, annual\nAnti-Money Laundering (AML) enterprise risk assessment and compliance training for all staff\n• Performing of ongoing compliance procedures such as the monitoring of Base Capital and Licensing Conditions\n• Submission of quarterly and annual MAS returns\n• Performing of Enterprise Risk Assessment on an annual basis\n• Performing of due diligence and annual reviews on outsourced service providers\n• Corresponding with the MAS Officer\nOther Duties:\n• Checking of the completeness of all investment documents after each round of funding\n• Preparing the agreements and other paperwork for share transfers, subscription of shares and transfer of\npartnership interest across all related entities and funds\n• Handling of company secretarial matters such as the preparation of board resolutions and liaising with the\ncorporate secretarial agents\n• Filing of FATCA returns for the group and fund entities on an annual basis\nEDUCATION\nUniversity of London Singapore\nBachelor of Science (Banking & Finance) 2013\n2nd Class Honours (Lower)\nNanyang Junior College Singapore\nGCE “A” Levels 2007\nLANGUAGES\nEnglish Native & Bilingual Proficiency\nMandarin Chinese Minimum Business Proficiency\nSKILLS\nMicrosoft Word, Excel & Powerpoint Professional Proficiency\n",
    "skills": [
      "communication",
      "excel",
      "finance"
    ],
    "experience": 8,
    "education": [
      "• A Compliance Officer with 3.5 years of experience in a venture capital firm that is regulated by the Monetary",
      "Authority of Singapore (“MAS”) under the Capital Market Services (CMS) Licence scheme",
      "• Analytical mind with clear, logical thought process",
      "• Excellent communication and written skills",
      "• Performing of ongoing compliance procedures such as the monitoring of Base Capital and Licensing Conditions",
      "• Filing of FATCA returns for the group and fund entities on an annual basis",
      "EDUCATION",
      "Bachelor of Science (Banking & Finance) 2013"
    ],
    "personal_info": {
      "email": "ryantangtg19@gmail.com",
      "phone": ""
    },
    "timestamp": "2025-06-12T11:11:58.292808"
  },
  {
    "file_path": "C:\\Users\\vasis\\Downloads\\resumeData\\Xander_Erwina Lau_Finance Compliance Executive.pdf",
    "name": "Lau Peiwen Erwina",
    "raw_text": "Lau Peiwen Erwina\n+65 90083183\nErwina_lau@hotmail.com\nDate of Birth: 29th March 1987\nResidency Status: Singapore Citizen\nLanguage Proficiency (Spoken and Written): English, Mandarin\nEducation\nCPA Australia\nCompleted the following professional modules:\n Ethics and governance\n Audit and assurance\n Contemporary Business Issues\n Strategic Management Accounting\n Financial Reporting\nRoyal Melbourne Institute of Technology (RMIT)\n Overall GPA 3.082 / 4 Bachelor of Business (Accountancy) with distinction\n Obtained high distinctions for Introductory Accounting, Macroeconomics 1, Financial Accounting and Business\nStatistics 1\n Obtained distinctions for Marketing Principles, Cost Management and Applications, Prices and Markets,\nSingapore Company Law, Corporate Accounting, Accounting Theory, Small Business and the Accountant, Ethical\nIssues in Accountancy and Introduction to Organizational Behaviour\nNgee Ann Polytechnic\nDiploma in Electronic and Computer Engineering (Telecommunication), 2008\n Overall GPA 3.48 / 4\n Class representative from 2006-2007\n Group leader for Final Year Project “Design of PCB Embedded Passive Devices”.\n Selected to provide Ansoft software training for employee of company for this joint industrial collaboration project.\nExperience\nJan 2016 – Xander Investment Management Pte. Ltd.\nPresent Finance and Compliance Executive\n Review and update Company’s internal polices (i.e. compliance manual, business continuity program\nmanual, risk management framework manual) to ensure that polices are in-line with the current MAS\nregulations and guidelines.\n Perform compliance monitoring and liaise with Company’s management and IT personnel to execute\nFY 2016 business continuity program.\n Perform KYC/AML checks for new investors.\n Other compliance matters (i.e. update of representatives directorships and shareholdings and MAS Surveys)\n Perform quarterly financial accounts and year end statutory financial reporting.\n Perform operational matters (i.e. preparing of board resolutions, setting up of fund entity and opening of bank\naccounts)\n Perform payroll related matters\n Liaise with internal and external auditors\nOct 2013 – Ernst & Young LLP\nNov 2015 Financial Services\nSenior 2\n Understanding of clients' businesses - processes, internal controls and segregation of duties\n Reconciling and analyzing of financial data and reports provided by client to ensure accuracy and compliance\nwith uniform accounting classifications\n Providing management with suggestions and input on how to improve control and audit mechanisms through\ninsightful analysis and investigation\n Reviewing of client’s preparation of financial statements and ensuring proper disclosure for the notes of the\nfinancial statement\n Ensure successful timely completion of assigned audit engagement\n Supervises and providing guidance to junior auditor\n Review work prepared by junior auditors, ensuring quality in compliance with professional standards\n Communicate with clients on the audit timeline\n Manage a portfolio of 21 audit engagements\nSept 2011 - RSM Chio Lim LLP\nOct 2013 General Audit Associate 2\n Understanding of clients' businesses - processes, internal controls and segregation of duties\n Reconciling and analyzing of financial data and reports provided by client to ensure accuracy and compliance\nwith uniform accounting classifications\n Providing management with suggestions and input on how to improve control and audit mechanisms through\ninsightful analysis and investigation\n Ensure successful timely completion of assigned audit engagement\n Preparation of financial statements and preparation of charts and tables to include in reports\nJun 2009 - Shihlin Franchise at Nex Serangoon\n2011 Assistant Manager\n Assisted the franchisee in research, marketing, finance, human resources and overall operations of the store.\n Co-manage the overall start-up of the franchise which generated the highest sales among other Shihlin outlets\nin their first month of operation.\nMarch - BHP Billiton\nMay 2008 Temporary HR Administrator\n Performed timely update of human resource database.\n Facilitated visa applications for expatriates and employees travelling.\n Involved in the planning of orientation activities for new employees.\nSkills and Interests\n Fluent in Mandarin and English\n Proficient in Microsoft Office Power Point, Microsoft Office Excel, Microsoft Office Words and GAMx\n Enjoy playing the piano (obtained Grade 8 certificate)\n Enjoy jogging, swimming, trekking and travelling\n",
    "skills": [
      "accounting",
      "excel",
      "finance"
    ],
    "experience": 0,
    "education": [
      "Education",
      " Overall GPA 3.082 / 4 Bachelor of Business (Accountancy) with distinction",
      " Obtained distinctions for Marketing Principles, Cost Management and Applications, Prices and Markets,",
      "Singapore Company Law, Corporate Accounting, Accounting Theory, Small Business and the Accountant, Ethical",
      "Diploma in Electronic and Computer Engineering (Telecommunication), 2008",
      "with uniform accounting classifications",
      " Communicate with clients on the audit timeline",
      "with uniform accounting classifications",
      " Facilitated visa applications for expatriates and employees travelling.",
      " Enjoy playing the piano (obtained Grade 8 certificate)"
    ],
    "personal_info": {
      "email": "Erwina_lau@hotmail.com",
      "phone": "+65 90083183"
    },
    "timestamp": "2025-06-12T11:11:58.446582"
  },
  {
    "file_path": "C:\\Users\\vasis\\Downloads\\resumeData\\Xander_Rohit Khandelwal_VP.pdf",
    "name": "Rohit Khandelwal",
    "raw_text": "ROHIT KHANDELWAL\n19 Shelford Road, #01 -25, Singapore, 288408\nrohitkhandelwal@live.in\n+65 8322 6870\nEducation\n2008 THE INSTITUTE OF CHARTERED ACCOUNTANTS OF INDIA NEW DELHI, INDIA\n Qualified chartered accountant with specialization in Financial & Treasury Management, Accountancy,\nTaxation, Valuation, Structuring, Risk Management and Compliance.\n Cleared all levels in first attempt and secured all India 47th rank in PEE-II (Level II)\n Completed certificate course on valuation\n2005 SRI RAM COLLEGE OF COMMERCE, UNIVERSITY OF DELHI NEW DELHI, INDIA\n Bachelor of Commerce (Honors) with first division.\n Specialisation in Financial Management, Taxation, Accountancy, Audit and Corporate Law.\nWork\nExperience THE XANDER GROUP\n2011-Present XANDER INVESTMENT MANAGEMENT PTE. LTD. SINGAPORE\n2009-2011 XANDER ADVISORS INDIA PRIVATE LIMITED NEW DELHI, INDIA\nVice President\n11 years’ experience spanning management of PE Funds and Family Offices, financial control, treasury\nmanagement, asset financing & leverage, currency hedging, transaction / fund structuring, fund operations &\nadministration, risk management and compliance, taxation and audit.\n Financial Control: Responsible for all aspects of financial control (such as treasury management, financial\naccounting, reporting, audits, taxation, risk management and regulatory compliance) for 30+ licensed and other\nentities operating across multiple jurisdictions such as Singapore, Mauritius, United States, United Kingdom,\nCayman Islands and India. Set-up compliance and finance functions in Singapore HQ.\n Treasury Management: Responsible for evaluating and managing investments in capital markets comprising\nof equities, fixed income securities, derivatives, structured products, alternative investments and commodities\nfor Group’s Family Office. Overseeing asset portfolio of over US$ 250 million.\n Currency Hedging: Responsible for evaluating and executing hedging strategies for PE funds and portfolio\ninvestments such as forward, options, call / put spreads, PAYG structures.\n Asset Financing & Leverage: Responsible for evaluating and executing leverage and asset monetization\nopportunities for PE funds and Family Office investments:\n Closed subscription line facilities of over US$ 125 million resulting in reduction of J-curve and enhancement\nof Fund IRR.\n Secured credit lines / asset financing of over US$ 30 million for Family Office Investments\n Fund Structuring and Closing: Worked on all aspects of structuring, investor due-diligence and closing of\nvarious PE Funds across multiple jurisdictions including Singapore, India, Mauritius and Cayman Islands:\n Opportunity Fund IV (vintage – 2011) comprising investor commitments of approx. US$ 225 million.\n Office Club Fund (vintage - 2014) comprising investor commitments of approx. US$ 200 million.\n Firm Level Initiatives: Responsible for firm level initiatives such as securing key regulatory approvals (i.e.\n‘Capital Market Services License’; ‘Exempt Fund Manager’) for conduct of fund management business in\nSingapore; securing key tax incentives for Fund Manager and PE Funds (i.e. ‘Financial Sector Incentive for Fund\nManagers’; ‘Enhanced Tier Exemption’) and other approvals across multiple jurisdictions for the Firm.\n Fund Operations & Administration: Supervising Fund Operations team in preparation of quarterly investor\nreports, investor queries, portfolio valuations, transaction structuring, investor operational due diligences, capital\ncalls & distributions, IRR and carry computations etc.\n Leadership & management: Reporting directly to Managing Partner and CEO. Extensive experience in\nworking with senior leadership teams. Participating in Senior Management & Investment Committee meetings.\nEnsuring firm wide implementation of approved policies and decisions. Managing team of 4 professionals.\n2005-2009 S.R.BATLIBOI (sole member of ERNST & YOUNG LLP in India) NEW DELHI, INDIA\nExecutive – Assurance & Advisory Business Services\nWorked on and led assurance and advisory assignments comprising of statutory audits, tax audits, group reporting of\nlisted global infrastructure firms and Initial Public Offering of leading real estate developers in Northern India.\nSelect work experience:\n Emaar MGF India: Review of financial and tax information forming part of the Initial Public Offering (‘IPO’)\ndocuments and assisting in the certification of the IPO documents; statutory audits – standalone and\nconsolidated; real estate project reviews etc.\n ALSTOM Group India (NSE: APIL): Statutory audits – standalone and consolidated; power and infrastructure\nproject reviews; quarterly reviews under SEBI provisions.\nPersonal Indian Citizen. Married. Fluent in English and Hindi. Enjoy traveling, music, movies and watching / playing\ncricket, volleyball and football.\n",
    "skills": [
      "accounting",
      "finance",
      "leadership"
    ],
    "experience": 11,
    "education": [
      "Education",
      " Completed certificate course on valuation",
      " Bachelor of Commerce (Honors) with first division.",
      "Cayman Islands and India. Set-up compliance and finance functions in Singapore HQ.",
      " Treasury Management: Responsible for evaluating and managing investments in capital markets comprising",
      "investments such as forward, options, call / put spreads, PAYG structures.",
      "various PE Funds across multiple jurisdictions including Singapore, India, Mauritius and Cayman Islands:",
      "‘Capital Market Services License’; ‘Exempt Fund Manager’) for conduct of fund management business in",
      "reports, investor queries, portfolio valuations, transaction structuring, investor operational due diligences, capital",
      "calls & distributions, IRR and carry computations etc.",
      "documents and assisting in the certification of the IPO documents; statutory audits – standalone and"
    ],
    "personal_info": {
      "email": "rohitkhandelwal@live.in",
      "phone": "+65 8322 6870"
    },
    "timestamp": "2025-06-12T11:11:58.556995"
  },
  {
    "file_path": "C:\\Users\\vasis\\Downloads\\resumeData\\Zhongtai International_Jonathan Man_Compliance Manager.pdf",
    "name": "Man Hoe Keung, Jonathan",
    "raw_text": "Man Hoe Keung, Jonathan\nPersonal Particulars\nDate of Birth : 08 Jan 1982\nNationality : Singapore / Permanent resident of Hong Kong\nAddress : BLK261B Sengkang East Way,\n#14-440\nS542261\nSingapore\nContact (Mobile) : 8128 8877\nContact (email) : Jonathanmanhk@gmail.com\nDate: Oct 2016 – present\nPosition: Compliance Manager\nCompany: Zhongtai International Holdings (Singapore) Pte. Ltd.\n• Start up\n• Sole compliance role hence involves licence application, policies, and procedures, etc\n• HR matters\n• IT matters\n• Any other matters\nPast employment:\nDate: Oct 2014 – July 2016\nPosition: Compliance Assistant Manager\nCompany: Invesco Asset Management Singapore Ltd\n• AML/KYC matters (e.g. onboarding, screening, review and reporting)\n• Liaison officer for MAS that include ad-hoc queries or completion of surveys and questionnaire\n• Compliance advisory (e.g. queries from the sales team that may include onboarding or regulations\nwithin Southeast Asia region, marketing team or other global initiatives)\n• Licensing matters (e.g. representatives, directors, etc)\n• Review of internal controls and procedure manuals (Licensing, Outsourcing, etc)\n• Conduct compliance/AML/Code of ethics/Gifts & Entertainment/Foreign representatives training\n• Handle and coordinate MAS inspection and statutory audit\n• Investment compliance using Charles River (e.g. Fair allocation. Disclosure of interest, trades\nmonitoring)\n• Review of regulations/consultation papers and impact analysis (Consultations, New, Amendments, etc)\n• Weekly Gifts and Entertainment reviews\n• Other ad-hoc projects (local or global)\nDate: Aug 2010 – October 2014\nPosition: Manager (Executive from August 2010 to December 2011, Assistant manager from January 2012 to\nDecember 2013)\nCompany: iFAST Financial Pte Ltd\n• Compliance monitoring/checks to ensure that the company processes are in compliance with the\nrelevant Acts and regulations, such as the Securities and Futures Act (SFA)/Financial Advisers Act\n(FAA)/CPF Investment Administrator Guidelines and internal policies\n• Review regulatory changes/consultation papers as and when necessary, communicate to the relevant\ndepartments if needed, and also discuss with relevant stakeholders on regulatory impact and necessary\nsystem or non-system changes\n• Liaise with and also prepare reports (e.g. regular reporting, surveys, ad-hoc queries) for submission to\nregulators (MAS and CPF Board)\n• Anti-Money Laundering (‘AML’) related matters (e.g. onboarding, screening, review and reporting)\n• Compliance advisory and licensing matters for both internal (e.g. business initiatives, sales queries, new\nproduct line (insurance)) and external parties (e.g. consultancy services, liaising with compliance\ndepartment of B2B clients, licence application)\n• Review of internal controls and procedures and is part of consultation and implementation process, both\nbusiness and non-business\n• Handling of complaints and investigations\n• Review of contracts, such as distribution agreements and service agreements (Compliance related\nclauses, e.g., FATCA, AML; terms are in line with outsourcing guidelines)\n• Maintenance of outsourcing register, annual review and ad-hoc review for new vendors\n• Maintenance of Compliance procedure manuals (update, review and amend)\n• Review of advertising and marketing materials\n• Conduct compliance/AML training\n• Cover for Hong Kong and Malaysia compliance team\n• Monitoring of suspicious transactions and reporting to STRO\n• Handle and coordinate MAS inspection and statutory audit\n• Manage, coordinate and/or implement projects, for example, Tax Crimes, FATCA, PDPA, etc\n• Supervisory role – hire, train, delegation of work, review of subordinate’s work and performance review\n• Assisted in IPO process\nDate: Dec 2008 - May 2010\nPosition: Senior Associate (Junior Executive )\nCompany: Stone Forest Corporate Advisory Pte Ltd\n• Recovery of assets\n• Liquidation and Litigation\n• Correspond and hold meetings with clients, lawyers, banks, Official Receiver, debtors, creditors, etc\n• Accounting duties and review of financial statements/company affairs\n• Investigation\n• Reports\n• Business development\n• Project management\nDate: Jun 2007 - Apr 2008\nPosition: Accounts Executive\nCompany: Oosh Pte Ltd\n• Accounting duties (Partial set)\n• Costing\nDate: Aug 2006 - Mar 2007 (Contract)\nPosition: Accounts Assistant\nCompany: Makino Asia Pte Ltd\n• Administrative and accounting duties\nOthers:\nSales Executive for 2nd hand car dealer, Telemarketer for Singtel and an IT training school, Market researcher for\nEuromonitor International, delivery man and courier driver for various companies. Have been a waiter, bartender\nand bar manager for various clubs in Singapore. Ran campaigns as a Project Supervisor for Publicis\nDialogue/Western Union as well. Was employed as an Interior Designer and Sales Consultant for about one and\nhalf year. Was a contract teacher in a local primary school.\nEducational Background\n- Bachelor's Degree in Accountancy/Banking Graduation Date: 2008\nMajor : Accounting\nInstitution/College : RMIT, Singapore\nDiploma in Compliance (accredited by ICA) - 2011\nD iploma in AML (accredited by ICA) - 2013\nLanguages\nLanguage / Dialects\nEnglish, Chinese, Cantonese, Hokkien\nAdditional information\nSkills\nMS Office (Word, Excel, PowerPoint)\nMYOB\nSyteline (ERP system)\nFact Accounting\nRaptor (Inventory control & purchasing system)\nSQL\nOther professional certification\nCMFAS M3\nCMFAS M5\nCMFAS M9\nHealth Insurance (SCI)\nCommGI (SCI)\nPGI (SCI)\nNational Service\nApril 2001 to Aug 2003\nVocation: RSL/ISL\nUnit/Squadron: FDS/Changi Airbase\nHighest rank: 3rd Sergeant\nMR: Apr 2015\n",
    "skills": [
      "accounting",
      "excel",
      "sql"
    ],
    "experience": 0,
    "education": [
      "• Sole compliance role hence involves licence application, policies, and procedures, etc",
      "• Investment compliance using Charles River (e.g. Fair allocation. Disclosure of interest, trades",
      "• Other ad-hoc projects (local or global)",
      "• Review regulatory changes/consultation papers as and when necessary, communicate to the relevant",
      "department of B2B clients, licence application)",
      "clauses, e.g., FATCA, AML; terms are in line with outsourcing guidelines)",
      "• Manage, coordinate and/or implement projects, for example, Tax Crimes, FATCA, PDPA, etc",
      "Sales Executive for 2nd hand car dealer, Telemarketer for Singtel and an IT training school, Market researcher for",
      "and bar manager for various clubs in Singapore. Ran campaigns as a Project Supervisor for Publicis",
      "half year. Was a contract teacher in a local primary school.",
      "Educational Background",
      "- Bachelor's Degree in Accountancy/Banking Graduation Date: 2008",
      "Diploma in Compliance (accredited by ICA) - 2011",
      "D iploma in AML (accredited by ICA) - 2013",
      "English, Chinese, Cantonese, Hokkien",
      "Other professional certification",
      "Vocation: RSL/ISL"
    ],
    "personal_info": {
      "email": "Jonathanmanhk@gmail.com",
      "phone": ""
    },
    "timestamp": "2025-06-12T11:11:58.808865"
  }
]
